Workbook
Name alumnos: 'Datos '!$B$2:$B$21
Name diagnostico: '09.Diagnostico'!$A$1:$F$52
Name fechaMEC: '07-CALENDARIO MEC'!$A$1:$C$52
Name indicadores: '08- INDICADORES AC'!$B$2:$E$52
Name tabla_registro: '05-BD- CUADRO ANECDOTICO'!$B$2:$F$633

Sheet Prinicipal
A1: INSTITUCION | G1: Promedio de Asistencia
A2: ESC.EXC. Manuel | D2: Dias de clase | E2: Viernes | G2: =+'03-ASISTENCIA'!D2 -> 0.99
A3: Molinas | D3: Horas ingreso | E3: 0.54166667
D4: Hora salida | E4: 0.63194444
A5: GRADO | D5: Receso | E5: 0.010416667
A6: SEPTIMO | D6: Horas cátedras | E6: =+(E4-E3)*3600/(40*60)-E5 -> 0.125
A8: TURNO | D8: INTRUMENTOS | J8: Plan Unidad 1
A9: MAÑANA | C9: 1 | D9: PLAN ANUAL | J9: Plan Unidad 2
C10: 2 | D10: REGISTRO DE TEMAS | J10: Plan Unidad 3
A11: ASIGNATURA | C11: 3 | D11: ASISTENCIA | J11: Plan Unidad 4
A12: FORMACIÓN ETICA | C12: 4 | D12: RSA | J12: Plan Unidad 5
C13: 5 | D13: CUADRO ANECDOTICO | J13: Plan Unidad 6
A14: PROFESOR | D14: INSTITUCIONAL | J14: Plan Unidad 7
A15: CHRISTHIAN KEIM | C15: 6 | D15: POA 2026 | J15: Plan Unidad 8
C16: 7 | D16: POA 2026 - ASIGNATURA | J16: Plan Unidad 9
A17: 2026 | C17: 8 | D17: CALENDARIO MEC | J17: Plan Unidad 10
C18: 9 | D18: PROYECTOS INSTITUCIONALES
C19: 10 | D19: INDICADORES ACTITUDINALES
C20: 11 | D20: DIAGNOSTICO

Sheet 01-PLAN ANUAL 
A1: Unidad Temática | B1: Capacidades | C1: Contenido | D1: Estrategias Didácticas | E1: Indicadores | F1: Estrategias evaluativas | G1: Recursos Didácticos
A2: Persona y entorno | B2: Reflexiona acerca de la práctica de los principios y valores democráticos. | C2: Ética y Moral. Diferencias y moralidad social. | D2: - Responde preguntas. | E2: - Identifica principios éticos y morales. | F2: - Portafolio de trabajo. | G2: - Cuadernillo Serie Poty.
A3: Persona y entorno | B3: Reflexiona acerca de la práctica de los principios y valores democráticos. | C3: Ética y Moral. Diferencias y moralidad social. | D3: - Establece diferencias entre ética y moral. | E3: - Diferencia moral y moralidad. | F3: - RSA con indicadores. | G3: - Cartulinas y pinceles.
A4: Persona y entorno | B4: Reflexiona acerca de la práctica de los principios y valores democráticos. | C4: Ética y Moral. Diferencias y moralidad social. | D4: - Diseña carteles de concientización.
A5: Persona y entorno | B5: Analiza dilemas éticos contemporáneos y su impacto social. | C5: **Escándalos éticos de nuestro tiempo:** Pobreza, hambre y mortalidad infantil. | D5: - Análisis de noticias actuales. | E5: - Reconoce problemáticas éticas globales. | F5: - Registro de observación. | G5: - Material de lectura.
A6: Persona y entorno | B6: Analiza dilemas éticos contemporáneos y su impacto social. | C6: **Escándalos éticos de nuestro tiempo:** Pobreza, hambre y mortalidad infantil. | D6: - Debate sobre déficit de agua potable. | E6: - Analiza causas de la mortalidad infantil. | F6: - Ensayos escritos. | G6: - Artículos de prensa.
A7: Persona y entorno | B7: Analiza dilemas éticos contemporáneos y su impacto social. | C7: **Escándalos éticos de nuestro tiempo:** Pobreza, hambre y mortalidad infantil. | D7: - Elaboración de ensayos breves.
A8: Persona y entorno | B8: Comprende la importancia de la convivencia armónica en el ámbito escolar. | C8: **Acuerdos de relacionamiento:** Código de convivencia docente-estudiante. | D8: - Lluvia de ideas sobre normas. | E8: - Valora el código de convivencia. | F8: - Participación activa. | G8: - Papelógrafos.
A9: Persona y entorno | B9: Comprende la importancia de la convivencia armónica en el ámbito escolar. | C9: **Acuerdos de relacionamiento:** Código de convivencia docente-estudiante. | D9: - Redacción participativa de acuerdos de aula. | E9: - Propone normas de respeto mutuo. | F9: - Documento de acuerdos. | G9: - Marcadores.
A10: Persona y entorno | B10: Identifica situaciones de acoso escolar y propone medidas de prevención. | C10: Bullying: Concepto, tipos, causas y consecuencias. | D10: (Abordaje > 2 horas) | E10: - Define tipos de bullying. | F10: - Guía de trabajo grupal. | G10: - Proyector / Videos.
A11: Persona y entorno | B11: Identifica situaciones de acoso escolar y propone medidas de prevención. | C11: Bullying: Concepto, tipos, causas y consecuencias. | D11: - Cine debate sobre casos reales. | E11: - Identifica consecuencias psicológicas.
A12: Persona y entorno | B12: Identifica situaciones de acoso escolar y propone medidas de prevención. | C12: Bullying: Concepto, tipos, causas y consecuencias. | D12: - Talleres de rol (agresor/víctima). | E12: - Propone acciones de prevención. | F12: - RSA. | G12: - Fichas de casos.
A13: Persona y entorno | B13: Identifica situaciones de acoso escolar y propone medidas de prevención. | C13: Bullying: Concepto, tipos, causas y consecuencias. | D13: - Elaboración de protocolos de ayuda.
A14: Persona y entorno | B14: Aplica técnicas básicas de resolución de conflictos en situaciones cotidianas. | C14: Mediación, Negociación y Confrontación. | D14: (Abordaje > 2 horas) | E14: - Diferencia mediación de negociación. | F14: - Evaluación de desempeño (Role-play). | G14: - Guiones de casos.
A15: Persona y entorno | B15: Aplica técnicas básicas de resolución de conflictos en situaciones cotidianas. | C15: Mediación, Negociación y Confrontación. | D15: - Simulacros de mediación escolar.
A16: Persona y entorno | B16: Aplica técnicas básicas de resolución de conflictos en situaciones cotidianas. | C16: Mediación, Negociación y Confrontación. | D16: - Ejercicios de comunicación asertiva. | E16: - Aplica pasos de la negociación asertiva. | G16: - Pizarra.
A17: Persona y entorno | B17: Aplica técnicas básicas de resolución de conflictos en situaciones cotidianas. | C17: Mediación, Negociación y Confrontación. | D17: - Análisis de casos de conflicto.
A18: La Familia | B18: Analiza la situación socioeconómica de las familias paraguayas. | C18: Pobreza y Canasta Básica Familiar. | D18: - Investigación de precios actuales. | E18: - Define el concepto de canasta básica. | F18: - Informe de investigación. | G18: - Datos estadísticos.
A19: La Familia | B19: Analiza la situación socioeconómica de las familias paraguayas. | C19: Pobreza y Canasta Básica Familiar. | D19: - Comparación de ingresos y costos básicos. | E19: - Analiza el impacto de la pobreza. | F19: - Cuadro comparativo. | G19: - Calculadora.
A20: La Familia | B20: Reconoce factores que inciden en la violencia intrafamiliar. | C20: Violencia Intrafamiliar: Causas y prevención. | D20: (Abordaje > 2 horas) | E20: - Identifica tipos de violencia familiar. | F20: - Cuestionario reflexivo. | G20: - Trípticos informativos.
A21: La Familia | B21: Reconoce factores que inciden en la violencia intrafamiliar. | C21: Violencia Intrafamiliar: Causas y prevención. | D21: - Charla con especialistas o videos informativos. | E21: - Conoce rutas de denuncia en Paraguay. | F21: - RSA. | G21: - Proyector.
A22: La Familia | B22: Reconoce factores que inciden en la violencia intrafamiliar. | C22: Violencia Intrafamiliar: Causas y prevención. | D22: - Análisis de la Ley contra violencia doméstica.
A23: La Familia | B23: Reconoce factores que inciden en la violencia intrafamiliar. | C23: Violencia Intrafamiliar: Causas y prevención. | D23: - Mapa de instituciones de denuncia.
A24: Derechos Humanos | B24: Reconoce los principios básicos que rigen los Derechos Humanos. | C24: Principios de los DD.HH.: Universalidad, progresividad e irreversibilidad. | D24: (Abordaje > 2 horas) | E24: - Explica la universalidad de los derechos. | F24: - Mapa conceptual. | G24: - Constitución Nacional.
A25: Derechos Humanos | B25: Reconoce los principios básicos que rigen los Derechos Humanos. | C25: Principios de los DD.HH.: Universalidad, progresividad e irreversibilidad. | D25: - Lectura comprensiva de la Declaración Universal.
A26: Derechos Humanos | B26: Reconoce los principios básicos que rigen los Derechos Humanos. | C26: Principios de los DD.HH.: Universalidad, progresividad e irreversibilidad. | D26: - Análisis de casos históricos. | E26: - Distingue progresividad de irreversibilidad. | F26: - Prueba escrita formativa. | G26: - Textos guía.
A27: Derechos Humanos | B27: Reconoce los principios básicos que rigen los Derechos Humanos. | C27: Principios de los DD.HH.: Universalidad, progresividad e irreversibilidad. | D27: - Debate sobre la temporalidad de los derechos.
A28: Derechos Humanos | B28: Analiza situaciones de vulneración de derechos en la niñez y adolescencia. | C28: **Causas de explotación:** Sexual, laboral y trabajos forzados. | D28: - Análisis de estadísticas nacionales. | E28: - Reconoce formas de explotación infantil. | F28: - Murales preventivos. | G28: - Afiches.
A29: Derechos Humanos | B29: Analiza situaciones de vulneración de derechos en la niñez y adolescencia. | C29: **Causas de explotación:** Sexual, laboral y trabajos forzados. | D29: - Identificación de señales de riesgo. | E29: - Valora la protección contra el trabajo forzado. | F29: - Portafolio. | G29: - Material audiovisual.
A30: Derechos Humanos | B30: Analiza situaciones de vulneración de derechos en la niñez y adolescencia. | C30: **Causas de explotación:** Sexual, laboral y trabajos forzados. | D30: - Elaboración de campañas preventivas.
A31: Democracia y Estado | B31: Analiza la situación de la mujer en la estructura social actual. | C31: **Pobreza, desigualdad y exclusión a la mujer.** | D31: - Debate sobre brecha salarial y acceso a educación. | E31: - Identifica factores de exclusión femenina. | F31: - RSA. | G31: - Material de lectura.
A32: Democracia y Estado | B32: Analiza la situación de la mujer en la estructura social actual. | C32: **Pobreza, desigualdad y exclusión a la mujer.** | D32: - Biografías de mujeres líderes en Paraguay. | E32: - Propone acciones para la igualdad. | F32: - Debate dirigido. | G32: - Artículos de género.
A33: Democracia y Estado | B33: Analiza el Sistema Tributario en función al fortalecimiento institucional. | C33: Sistema Tributario y funciones de la S.E.T. | D33: (Abordaje > 2 horas) | E33: - Identifica la función tributaria. | F33: - Ejercicios prácticos. | G33: - Formularios de práctica.
A34: Democracia y Estado | B34: Analiza el Sistema Tributario en función al fortalecimiento institucional. | C34: Sistema Tributario y funciones de la S.E.T. | D34: - Taller sobre el IVA y su importancia social.
A35: Democracia y Estado | B35: Analiza el Sistema Tributario en función al fortalecimiento institucional. | C35: Sistema Tributario y funciones de la S.E.T. | D35: - Visita virtual o análisis de la página de la SET. | E35: - Valora la función social de los tributos. | F35: - Portafolio. | G35: - Internet.
A36: Democracia y Estado | B36: Analiza el Sistema Tributario en función al fortalecimiento institucional. | C36: Sistema Tributario y funciones de la S.E.T. | D36: - Ejercicios de cálculo básico de impuestos.
A37: Democracia y Estado | B37: Analiza la estructura y funciones de los organismos del Estado. | C37: Ministerio de Hacienda y Autoridades Locales (Intendencias/Gobernaciones). | D37: - Elaboración de organigrama del Estado. | E37: - Reconoce funciones del Ministerio de Hacienda. | F37: - Mapa conceptual. | G37: - Organigrama estatal.
A38: Democracia y Estado | B38: Analiza la estructura y funciones de los organismos del Estado. | C38: Ministerio de Hacienda y Autoridades Locales (Intendencias/Gobernaciones). | D38: - Investigación sobre funciones municipales. | E38: - Diferencia roles de Intendentes y Gobernadores. | F38: - RSA. | G38: - Páginas web oficiales.
A39: Democracia y Estado | B39: Analiza la estructura y funciones de los organismos del Estado. | C39: Ministerio de Hacienda y Autoridades Locales (Intendencias/Gobernaciones). | D39: - Entrevista a autoridades o análisis de gestión.

Sheet 02-REGISTRO DE TEMAS
A1: PLANILLA DE EJECUCIÓN DE CLASES | D1: 2026
B2: Plan de Clases | C2: ESTADO | D2: Ejecutado
A3: =+'03-ASISTENCIA'!F4 -> 46084
A4: =+'03-ASISTENCIA'!G4 -> 46090
A5: 46097 | B5: Moral Social | C5: =IFERROR(VLOOKUP(A5, fechaMEC, 3, FALSE), "Clase Normal") -> Clase Normal | D5: =IFERROR(VLOOKUP(A5, fechaMEC, 2, FALSE), "Ejecutado") -> Ejecutado
A6: =+'03-ASISTENCIA'!I4 -> 46104 | C6: =IFERROR(VLOOKUP(A6, fechaMEC, 3, FALSE), "Clase Normal") -> Clase Normal | D6: =IFERROR(VLOOKUP(A6, fechaMEC, 2, FALSE), "Ejecutado") -> Ejecutado | F6: Fecha (DD/MM/YYYY) | G6: Evento / Conmemoración | H6: Tipo
A7: 46111 | B7: La responsabilidad | C7: =IFERROR(VLOOKUP(A7, fechaMEC, 3, FALSE), "Clase Normal") -> Clase Normal | D7: =IFERROR(VLOOKUP(A7, fechaMEC, 2, FALSE), "Ejecutado") -> Ejecutado | F7: 46023 | G7: Año Nuevo | H7: Feriado Nacional
A8: =+'03-ASISTENCIA'!K4 -> 46118 | F8: 46063 | G8: Apertura Institucional y Retorno Docente | H8: MEC - INSTITUCIONAL
A9: 46125 | B9: Elabora un mapa mental de Moral Social ( Trabajo remitido por WS) | C9: Alumnos con gripe en su mayoria | D9: =IFERROR(VLOOKUP(A9, fechaMEC, 2, FALSE), "Ejecutado") -> Ejecutado | F9: 46076 | G9: Inicio de Clases (Sector Oficial) | H9: MEC - INSTITUCIONAL
A10: 46132 | B10: Moral Individual / El ser y deber ser | C10: =IFERROR(VLOOKUP(A10, fechaMEC, 3, FALSE), "Clase Normal") -> Clase Normal | D10: =IFERROR(VLOOKUP(A10, fechaMEC, 2, FALSE), "Ejecutado") -> Ejecutado | F10: 46077 | G10: Día de la Mujer Paraguaya (Homenaje a las Residentas) | H10: Dia para conmemorar
C11: =IFERROR(VLOOKUP(#REF!, fechaMEC, 3, FALSE), "Clase Normal") -> Clase Normal | D11: =IFERROR(VLOOKUP(#REF!, fechaMEC, 2, FALSE), "Ejecutado") -> Ejecutado | F11: 46082 | G11: Día de los Héroes | H11: Feriado Nacional
C12: =IFERROR(VLOOKUP(A12, fechaMEC, 3, FALSE), "Clase Normal") -> Clase Normal | D12: =IFERROR(VLOOKUP(A12, fechaMEC, 2, FALSE), "Ejecutado") -> Ejecutado | F12: 46082 | G12: Día de los Héroes (Muerte del Mcal. López en Cerro Corá) | H12: Dia para conmemorar
C13: =IFERROR(VLOOKUP(A13, fechaMEC, 3, FALSE), "Clase Normal") -> Clase Normal | D13: =IFERROR(VLOOKUP(A13, fechaMEC, 2, FALSE), "Ejecutado") -> Ejecutado | F13: 46102 | G13: Día Mundial de la Poesía y Día del Síndrome de Down | H13: Dia para conmemorar
C14: =IFERROR(VLOOKUP(A14, fechaMEC, 3, FALSE), "Clase Normal") -> Clase Normal | F14: 46114 | G14: Jueves Santo (Receso) | H14: Feriado Nacional
C15: =IFERROR(VLOOKUP(A15, fechaMEC, 3, FALSE), "Clase Normal") -> Clase Normal | D15: =IFERROR(VLOOKUP(A15, fechaMEC, 2, FALSE), "Ejecutado") -> Ejecutado | F15: 46115 | G15: Viernes Santo (Receso) | H15: Feriado Nacional
C16: =IFERROR(VLOOKUP(A16, fechaMEC, 3, FALSE), "Clase Normal") -> Clase Normal | F16: 46135 | G16: Día del Libro y del Derecho de Autor | H16: Dia para conmemorar
C17: =IFERROR(VLOOKUP(A17, fechaMEC, 3, FALSE), "Clase Normal") -> Clase Normal | D17: =IFERROR(VLOOKUP(A17, fechaMEC, 2, FALSE), "Ejecutado") -> Ejecutado | F17: 46138 | G17: Día del Periodista (Muerte de Santiago Leguizamón) | H17: Dia para conmemorar
C18: =IFERROR(VLOOKUP(A18, fechaMEC, 3, FALSE), "Clase Normal") -> Clase Normal | F18: 46142 | G18: Día del Maestro (En Paraguay) | H18: Dia para conmemorar
C19: =IFERROR(VLOOKUP(A19, fechaMEC, 3, FALSE), "Clase Normal") -> Clase Normal | F19: 46143 | G19: Día de los Trabajadores | H19: Feriado Nacional
C20: =IFERROR(VLOOKUP(A20, fechaMEC, 3, FALSE), "Clase Normal") -> Clase Normal | F20: 46156 | G20: Día de la Independencia Nacional | H20: Feriado Nacional
C21: =IFERROR(VLOOKUP(A21, fechaMEC, 3, FALSE), "Clase Normal") -> Clase Normal | D21: =IFERROR(VLOOKUP(A21, fechaMEC, 2, FALSE), "Ejecutado") -> Ejecutado | F21: 46156 | G21: Día de la Madre | H21: Dia para conmemorar
C22: =IFERROR(VLOOKUP(A22, fechaMEC, 3, FALSE), "Clase Normal") -> Clase Normal | D22: =IFERROR(VLOOKUP(A22, fechaMEC, 2, FALSE), "Ejecutado") -> Ejecutado | F22: 46157 | G22: Día de la Independencia Nacional | H22: Feriado Nacional
C23: =IFERROR(VLOOKUP(A23, fechaMEC, 3, FALSE), "Clase Normal") -> Clase Normal | F23: 46157 | G23: Día de la Independencia Nacional | H23: Dia para conmemorar
B24: Examen Primera Etapa | C24: =IFERROR(VLOOKUP(A24, fechaMEC, 3, FALSE), "Clase Normal") -> Clase Normal | F24: 46171 | G24: Día del Ejército Paraguayo | H24: Dia para conmemorar
C25: =IFERROR(VLOOKUP(A25, fechaMEC, 3, FALSE), "Clase Normal") -> Clase Normal | F25: 46185 | G25: Paz del Chaco | H25: Feriado Nacional
B26: Vacaciones de Invierno | C26: =IFERROR(VLOOKUP(A26, fechaMEC, 3, FALSE), "Clase Normal") -> Clase Normal | D26: =IFERROR(VLOOKUP(A26, fechaMEC, 2, FALSE), "Ejecutado") -> Ejecutado | F26: 46185 | G26: Paz del Chaco (Firma del Protocolo de Paz, 1935) | H26: Asueto - Departamental / Desfile
B27: Vacaciones de Invierno | C27: =IFERROR(VLOOKUP(A27, fechaMEC, 3, FALSE), "Clase Normal") -> Clase Normal | D27: =IFERROR(VLOOKUP(A27, fechaMEC, 2, FALSE), "Ejecutado") -> Ejecutado | F27: 46192 | G27: Día del Árbol (En Paraguay) | H27: Clase Normal
C28: =IFERROR(VLOOKUP(A28, fechaMEC, 3, FALSE), "Clase Normal") -> Clase Normal | F28: 46216 | G28: Inicio Vacaciones de Invierno | H28: MEC - VACACIONES
C29: =IFERROR(VLOOKUP(A29, fechaMEC, 3, FALSE), "Clase Normal") -> Clase Normal | F29: 46217 | G29: Inicio Vacaciones de Invierno | H29: MEC - VACACIONES
C30: =IFERROR(VLOOKUP(A30, fechaMEC, 3, FALSE), "Clase Normal") -> Clase Normal | D30: =IFERROR(VLOOKUP(A30, fechaMEC, 2, FALSE), "Ejecutado") -> Ejecutado | F30: 46218 | G30: Inicio Vacaciones de Invierno | H30: MEC - VACACIONES
C31: =IFERROR(VLOOKUP(A31, fechaMEC, 3, FALSE), "Clase Normal") -> Clase Normal | F31: 46219 | G31: Inicio Vacaciones de Invierno | H31: MEC - VACACIONES
C32: =IFERROR(VLOOKUP(A32, fechaMEC, 3, FALSE), "Clase Normal") -> Clase Normal | F32: 46220 | G32: Inicio Vacaciones de Invierno | H32: MEC - VACACIONES
C33: =IFERROR(VLOOKUP(A33, fechaMEC, 3, FALSE), "Clase Normal") -> Clase Normal | F33: 46221 | G33: Inicio Vacaciones de Invierno | H33: MEC - VACACIONES
C34: =IFERROR(VLOOKUP(A34, fechaMEC, 3, FALSE), "Clase Normal") -> Clase Normal | F34: 46222 | G34: Inicio Vacaciones de Invierno | H34: MEC - VACACIONES
C35: =IFERROR(VLOOKUP(A35, fechaMEC, 3, FALSE), "Clase Normal") -> Clase Normal | F35: 46223 | G35: Inicio Vacaciones de Invierno | H35: MEC - VACACIONES
C36: =IFERROR(VLOOKUP(A36, fechaMEC, 3, FALSE), "Clase Normal") -> Clase Normal | F36: 46224 | G36: Inicio Vacaciones de Invierno | H36: MEC - VACACIONES
C37: =IFERROR(VLOOKUP(A37, fechaMEC, 3, FALSE), "Clase Normal") -> Clase Normal | F37: 46225 | G37: Inicio Vacaciones de Invierno | H37: MEC - VACACIONES
B38: Examen Segunda Etapa | C38: =IFERROR(VLOOKUP(A38, fechaMEC, 3, FALSE), "Clase Normal") -> Clase Normal | F38: 46226 | G38: Inicio Vacaciones de Invierno | H38: MEC - VACACIONES
C39: =IFERROR(VLOOKUP(A39, fechaMEC, 3, FALSE), "Clase Normal") -> Clase Normal | F39: 46227 | G39: Fin Vacaciones de Invierno | H39: MEC - VACACIONES
C40: =IFERROR(VLOOKUP(A40, fechaMEC, 3, FALSE), "Clase Normal") -> Clase Normal | D40: =IFERROR(VLOOKUP(A40, fechaMEC, 2, FALSE), "Ejecutado") -> Ejecutado | F40: 46227 | G40: Natalicio del Mcal. Francisco Solano López | H40: Dia para conmemorar
C41: =IFERROR(VLOOKUP(A41, fechaMEC, 3, FALSE), "Clase Normal") -> Clase Normal | F41: 46233 | G41: Día de la Amistad (Cruzada Mundial de la Amistad) | H41: Dia para conmemorar
C42: =IFERROR(VLOOKUP(A42, fechaMEC, 3, FALSE), "Clase Normal") -> Clase Normal | F42: 46248 | G42: Día de la Bandera | H42: Dia para conmemorar
C43: =IFERROR(VLOOKUP(A43, fechaMEC, 3, FALSE), "Clase Normal") -> Clase Normal | F43: 46249 | G43: Fundación de Asunción | H43: Feriado Nacional
C44: =IFERROR(VLOOKUP(A44, fechaMEC, 3, FALSE), "Clase Normal") -> Clase Normal | F44: 46249 | G44: Fundación de Asunción y Día del Niño (En Paraguay) | H44: Dia para conmemorar
C45: =IFERROR(VLOOKUP(A45, fechaMEC, 3, FALSE), "Clase Normal") -> Clase Normal | F45: 46250 | G45: Día de los Niños Mártires de Acosta Ñu | H45: Dia para conmemorar
F46: 46256 | G46: Día del Folklore Paraguayo | H46: Dia para conmemorar
F47: 46259 | G47: Día del Idioma Guaraní | H47: Dia para conmemorar
F48: 46286 | G48: Día de la Juventud y de la Primavera | H48: Clase Normal
F49: 46294 | G49: Victoria de Boquerón | H49: Feriado Nacional
F50: 46294 | G50: Batalla de Boquerón (Victoria paraguaya, 1932) | H50: Dia para conmemorar
F51: 46307 | G51: Día de la Raza (Descubrimiento de América) | H51: Dia para conmemorar
F52: 46318 | G52: Día del Diseñador Gráfico y del Radiooperador | H52: Dia para conmemorar
F53: 46351 | G53: Día Internacional de la Eliminación de la Violencia contra la Mujer | H53: Dia para conmemorar
F54: 46356 | G54: Finalización de Clases | H54: MEC - CIERRE PEDAGOGICAS
F55: 46364 | G55: Día de la Virgen de Caacupé | H55: Feriado Nacional
F56: 46367 | G56: Cierre de Actividades Administrativas | H56: MEC - CIERRE ADM.
F57: 46381 | G57: Navidad | H57: Feriado Nacional

Sheet 03-ASISTENCIA
C2: PLANILLA DE ASISTENCIA | D2: =+AVERAGE(D5:D24) -> 0.99 | N2: SEPTIMO
F3: =+F48 -> 0 | G3: =+G48 -> 0 | H3: =+H48 -> Moral Social | I3: =+I48 -> 0 | J3: =+J48 -> La responsabilidad | K3: =+K48 -> 0 | L3: =+L48 -> Elabora un mapa mental de Moral Social ( Trabajo remitido por WS) | M3: =+M48 -> 0 | ... S3: =+S48 -> 0
A4: N° Orden | B4: filtrar | C4: Apellido/s Nombre/s | D4: % DE ASISTENCIA | E4: FIRMAS | F4: 46084 | G4: 46090 | H4: 46097 | I4: 46104 | J4: 46111 | K4: 46118 | L4: 46125 | M4: 46132 | N4: 46139 | O4: 46146 | P4: 46153 | AS4: Fecha (DD/MM/YYYY) | AT4: Evento / Conmemoración | AU4: Tipo | EM4: =+TODAY() -> 46146
A5: 1 | B5: X | C5: =+'Datos '!B2 -> NAHIARA ARCE | D5: =_xlfn.LET(_xlpm.rango, F5:AI5, (COUNTIF(_xlpm.rango, "P") + COUNTIF(_xlpm.rango, "PF")) / (COUNTIF(_xlpm.rango, "P") + COUNTIF(_xlpm.rango, "A") + COUNTIF(_xlpm.rango, "PF"))) -> 1 | E5: =COUNTIF(F5:V5,"PF") -> 2 | H5: PF | J5: PF | L5: PF | M5: PFC | AS5: 46023 | AT5: Año Nuevo | AU5: Feriado Nacional
A6: 2 | B6: xx | C6: =+'Datos '!B3 -> GUADALUPE ARCE | D6: =_xlfn.LET(_xlpm.rango, F6:AI6, (COUNTIF(_xlpm.rango, "P") + COUNTIF(_xlpm.rango, "PF")) / (COUNTIF(_xlpm.rango, "P") + COUNTIF(_xlpm.rango, "A") + COUNTIF(_xlpm.rango, "PF"))) -> 0.8 | E6: =COUNTIF(F6:V6,"PF") -> 3 | F6: PF | J6: PF | L6: PF | M6: P | O6: a | AS6: 46063 | AT6: Apertura Institucional y Retorno Docente | AU6: MEC - INSTITUCIONAL
A7: 3 | B7: X | C7: =+'Datos '!B4 -> ALMA AYALA | D7: =_xlfn.LET(_xlpm.rango, F7:AI7, (COUNTIF(_xlpm.rango, "P") + COUNTIF(_xlpm.rango, "PF")) / (COUNTIF(_xlpm.rango, "P") + COUNTIF(_xlpm.rango, "A") + COUNTIF(_xlpm.rango, "PF"))) -> 1 | E7: =COUNTIF(F7:V7,"PF") -> 4 | H7: pf | J7: PF | L7: PF | M7: pf | AS7: 46076 | AT7: Inicio de Clases (Sector Oficial) | AU7: MEC - INSTITUCIONAL
A8: 4 | B8: x | C8: =+'Datos '!B5 -> GUADALUPE BARRETO | D8: =_xlfn.LET(_xlpm.rango, F8:AI8, (COUNTIF(_xlpm.rango, "P") + COUNTIF(_xlpm.rango, "PF")) / (COUNTIF(_xlpm.rango, "P") + COUNTIF(_xlpm.rango, "A") + COUNTIF(_xlpm.rango, "PF"))) -> 1 | E8: =COUNTIF(F8:V8,"PF") -> 3 | F8: PF | G8: P | H8: PF | I8: ´P | J8: Bandaliza | L8: PF | M8: PFF | AS8: 46077 | AT8: Día de la Mujer Paraguaya (Homenaje a las Residentas) | AU8: Dia para conmemorar
A9: 5 | B9: X | C9: =+'Datos '!B6 -> LUIS BARRIOS | D9: =_xlfn.LET(_xlpm.rango, F9:AI9, (COUNTIF(_xlpm.rango, "P") + COUNTIF(_xlpm.rango, "PF")) / (COUNTIF(_xlpm.rango, "P") + COUNTIF(_xlpm.rango, "A") + COUNTIF(_xlpm.rango, "PF"))) -> 1 | E9: =COUNTIF(F9:V9,"PF") -> 4 | I9: PF | J9: PF | L9: PF | M9: PF | AS9: 46082 | AT9: Día de los Héroes | AU9: Feriado Nacional
A10: 6 | B10: x | C10: =+'Datos '!B7 -> LUANA BENITEZ | D10: =_xlfn.LET(_xlpm.rango, F10:AI10, (COUNTIF(_xlpm.rango, "P") + COUNTIF(_xlpm.rango, "PF")) / (COUNTIF(_xlpm.rango, "P") + COUNTIF(_xlpm.rango, "A") + COUNTIF(_xlpm.rango, "PF"))) -> 1 | E10: =COUNTIF(F10:V10,"PF") -> 3 | H10: PF | J10: PF | L10: PF | M10: PFC | AS10: 46082 | AT10: Día de los Héroes (Muerte del Mcal. López en Cerro Corá) | AU10: Dia para conmemorar
A11: 7 | B11: x | C11: =+'Datos '!B8 -> CARLOS CABALLERO | D11: =_xlfn.LET(_xlpm.rango, F11:AI11, (COUNTIF(_xlpm.rango, "P") + COUNTIF(_xlpm.rango, "PF")) / (COUNTIF(_xlpm.rango, "P") + COUNTIF(_xlpm.rango, "A") + COUNTIF(_xlpm.rango, "PF"))) -> 1 | E11: =COUNTIF(F11:V11,"PF") -> 2 | H11: PF | J11: PC | L11: PF | AS11: 46102 | AT11: Día Mundial de la Poesía y Día del Síndrome de Down | AU11: Dia para conmemorar
A12: 8 | B12: x | C12: =+'Datos '!B9 -> THAIS CACERES | D12: =_xlfn.LET(_xlpm.rango, F12:AI12, (COUNTIF(_xlpm.rango, "P") + COUNTIF(_xlpm.rango, "PF")) / (COUNTIF(_xlpm.rango, "P") + COUNTIF(_xlpm.rango, "A") + COUNTIF(_xlpm.rango, "PF"))) -> 1 | E12: =COUNTIF(F12:V12,"PF") -> 3 | H12: pf | J12: pf | L12: PF | M12: PFF | AS12: 46114 | AT12: Jueves Santo (Receso) | AU12: Feriado Nacional
A13: 9 | B13: x | C13: =+'Datos '!B10 -> MAXIMO DIAZ | D13: =_xlfn.LET(_xlpm.rango, F13:AI13, (COUNTIF(_xlpm.rango, "P") + COUNTIF(_xlpm.rango, "PF")) / (COUNTIF(_xlpm.rango, "P") + COUNTIF(_xlpm.rango, "A") + COUNTIF(_xlpm.rango, "PF"))) -> 1 | E13: =COUNTIF(F13:V13,"PF") -> 2 | H13: PFC | J13: PF | L13: PF | M13: PFC | AS13: 46115 | AT13: Viernes Santo (Receso) | AU13: Feriado Nacional
A14: 10 | B14: x | C14: =+'Datos '!B11 -> BASTTIAN ESTIGARRIBIA | D14: =_xlfn.LET(_xlpm.rango, F14:AI14, (COUNTIF(_xlpm.rango, "P") + COUNTIF(_xlpm.rango, "PF")) / (COUNTIF(_xlpm.rango, "P") + COUNTIF(_xlpm.rango, "A") + COUNTIF(_xlpm.rango, "PF"))) -> 1 | E14: =COUNTIF(F14:V14,"PF") -> 4 | H14: PF | J14: PF | L14: PF | M14: PF | AS14: 46135 | AT14: Día del Libro y del Derecho de Autor | AU14: Dia para conmemorar
A15: 11 | B15: x | C15: =+'Datos '!B12 -> IVONNE FERNANDEZ | D15: =_xlfn.LET(_xlpm.rango, F15:AI15, (COUNTIF(_xlpm.rango, "P") + COUNTIF(_xlpm.rango, "PF")) / (COUNTIF(_xlpm.rango, "P") + COUNTIF(_xlpm.rango, "A") + COUNTIF(_xlpm.rango, "PF"))) -> 1 | E15: =COUNTIF(F15:V15,"PF") -> 4 | H15: PF | J15: PF | L15: PF | M15: PF | AS15: 46138 | AT15: Día del Periodista (Muerte de Santiago Leguizamón) | AU15: Dia para conmemorar
A16: 12 | B16: x | C16: =+'Datos '!B13 -> EMILIA FERNANDEZ | D16: =_xlfn.LET(_xlpm.rango, F16:AI16, (COUNTIF(_xlpm.rango, "P") + COUNTIF(_xlpm.rango, "PF")) / (COUNTIF(_xlpm.rango, "P") + COUNTIF(_xlpm.rango, "A") + COUNTIF(_xlpm.rango, "PF"))) -> 1 | E16: =COUNTIF(F16:V16,"PF") -> 2 | H16: PFC | J16: PF | L16: PF | M16: PFC | AS16: 46142 | AT16: Día del Maestro (En Paraguay) | AU16: Dia para conmemorar
A17: 13 | B17: x | C17: =+'Datos '!B14 -> TAMARA FLORENTIN | D17: =_xlfn.LET(_xlpm.rango, F17:AI17, (COUNTIF(_xlpm.rango, "P") + COUNTIF(_xlpm.rango, "PF")) / (COUNTIF(_xlpm.rango, "P") + COUNTIF(_xlpm.rango, "A") + COUNTIF(_xlpm.rango, "PF"))) -> 1 | E17: =COUNTIF(F17:V17,"PF") -> 3 | I17: PF | J17: PF | K17: PF | L17: PFC | M17: PFC | AS17: 46143 | AT17: Día de los Trabajadores | AU17: Feriado Nacional
A18: 14 | B18: x | C18: =+'Datos '!B15 -> AYLEN FLORENTIN | D18: =_xlfn.LET(_xlpm.rango, F18:AI18, (COUNTIF(_xlpm.rango, "P") + COUNTIF(_xlpm.rango, "PF")) / (COUNTIF(_xlpm.rango, "P") + COUNTIF(_xlpm.rango, "A") + COUNTIF(_xlpm.rango, "PF"))) -> 1 | E18: =COUNTIF(F18:V18,"PF") -> 4 | H18: PF | J18: PF | L18: PF | M18: PF | AS18: 46156 | AT18: Día de la Independencia Nacional | AU18: Feriado Nacional
A19: 15 | B19: x | C19: =+'Datos '!B16 -> PAULA FRANCO | D19: =_xlfn.LET(_xlpm.rango, F19:AI19, (COUNTIF(_xlpm.rango, "P") + COUNTIF(_xlpm.rango, "PF")) / (COUNTIF(_xlpm.rango, "P") + COUNTIF(_xlpm.rango, "A") + COUNTIF(_xlpm.rango, "PF"))) -> 1 | E19: =COUNTIF(F19:V19,"PF") -> 3 | H19: PF | J19: PF | L19: PF | M19: PFF | AS19: 46156 | AT19: Día de la Madre | AU19: Dia para conmemorar
A20: 16 | B20: x | C20: =+'Datos '!B17 -> JEANELLY GAONA | D20: =_xlfn.LET(_xlpm.rango, F20:AI20, (COUNTIF(_xlpm.rango, "P") + COUNTIF(_xlpm.rango, "PF")) / (COUNTIF(_xlpm.rango, "P") + COUNTIF(_xlpm.rango, "A") + COUNTIF(_xlpm.rango, "PF"))) -> 1 | E20: =COUNTIF(F20:V20,"PF") -> 3 | H20: pf | J20: pf | L20: PF | M20: PFC | AS20: 46157 | AT20: Día de la Independencia Nacional | AU20: Feriado Nacional
A21: 17 | B21: X | C21: =+'Datos '!B18 -> LUANA GAONA | D21: =_xlfn.LET(_xlpm.rango, F21:AI21, (COUNTIF(_xlpm.rango, "P") + COUNTIF(_xlpm.rango, "PF")) / (COUNTIF(_xlpm.rango, "P") + COUNTIF(_xlpm.rango, "A") + COUNTIF(_xlpm.rango, "PF"))) -> 1 | E21: =COUNTIF(F21:V21,"PF") -> 3 | H21: PF | J21: PF | L21: PF | AS21: 46157 | AT21: Día de la Independencia Nacional | AU21: Dia para conmemorar
A22: 18 | B22: x | C22: =+'Datos '!B19 -> ABIGAIL GARCIA | D22: =_xlfn.LET(_xlpm.rango, F22:AI22, (COUNTIF(_xlpm.rango, "P") + COUNTIF(_xlpm.rango, "PF")) / (COUNTIF(_xlpm.rango, "P") + COUNTIF(_xlpm.rango, "A") + COUNTIF(_xlpm.rango, "PF"))) -> 1 | E22: =COUNTIF(F22:V22,"PF") -> 3 | H22: pf | J22: pf | L22: PF | M22: PFF | AS22: 46171 | AT22: Día del Ejército Paraguayo | AU22: Dia para conmemorar
A23: 19 | B23: x | C23: =+'Datos '!B20 -> LAUTARO GARCIA | D23: =_xlfn.LET(_xlpm.rango, F23:AI23, (COUNTIF(_xlpm.rango, "P") + COUNTIF(_xlpm.rango, "PF")) / (COUNTIF(_xlpm.rango, "P") + COUNTIF(_xlpm.rango, "A") + COUNTIF(_xlpm.rango, "PF"))) -> 1 | E23: =COUNTIF(F23:V23,"PF") -> 2 | L23: PF | M23: PF | AS23: 46185 | AT23: Paz del Chaco | AU23: Feriado Nacional
A24: 20 | B24: x | C24: =+'Datos '!B21 -> SANTIAGO GIMENEZ | D24: =_xlfn.LET(_xlpm.rango, F24:AI24, (COUNTIF(_xlpm.rango, "P") + COUNTIF(_xlpm.rango, "PF")) / (COUNTIF(_xlpm.rango, "P") + COUNTIF(_xlpm.rango, "A") + COUNTIF(_xlpm.rango, "PF"))) -> 1 | E24: =COUNTIF(F24:V24,"PF") -> 3 | H24: pf | J24: pf | L24: PF | M24: PFC | AS24: 46185 | AT24: Paz del Chaco (Firma del Protocolo de Paz, 1935) | AU24: Asueto - Departamental / Desfile
A25: 21 | B25: x | C25: =+'Datos '!B22 -> SANTIAGO GIRETT | D25: =_xlfn.LET(_xlpm.rango, F25:AI25, (COUNTIF(_xlpm.rango, "P") + COUNTIF(_xlpm.rango, "PF")) / (COUNTIF(_xlpm.rango, "P") + COUNTIF(_xlpm.rango, "A") + COUNTIF(_xlpm.rango, "PF"))) -> 1 | E25: =COUNTIF(F25:V25,"PF") -> 4 | H25: PF | J25: pf | K25: pf | L25: PF | M25: pfc | AS25: 46192 | AT25: Día del Árbol (En Paraguay) | AU25: Clase Normal
A26: 22 | B26: X | C26: =+'Datos '!B23 -> FREDY GOMEZ | D26: =_xlfn.LET(_xlpm.rango, F26:AI26, (COUNTIF(_xlpm.rango, "P") + COUNTIF(_xlpm.rango, "PF")) / (COUNTIF(_xlpm.rango, "P") + COUNTIF(_xlpm.rango, "A") + COUNTIF(_xlpm.rango, "PF"))) -> 1 | E26: =COUNTIF(F26:V26,"PF") -> 0 | H26: P | J26: P | L26: P | M26: P | R26: No tiene cuaderno | AS26: 46216 | AT26: Inicio Vacaciones de Invierno | AU26: MEC - VACACIONES
A27: 23 | B27: x | C27: =+'Datos '!B24 -> BETHANIA GONZALEZ | D27: =_xlfn.LET(_xlpm.rango, F27:AI27, (COUNTIF(_xlpm.rango, "P") + COUNTIF(_xlpm.rango, "PF")) / (COUNTIF(_xlpm.rango, "P") + COUNTIF(_xlpm.rango, "A") + COUNTIF(_xlpm.rango, "PF"))) -> 1 | E27: =COUNTIF(F27:V27,"PF") -> 3 | H27: pf | J27: p | K27: pfc | L27: PF | M27: pf | AS27: 46217 | AT27: Inicio Vacaciones de Invierno | AU27: MEC - VACACIONES
A28: 24 | B28: X | C28: =+'Datos '!B25 -> SHEYLA IRALA | D28: =_xlfn.LET(_xlpm.rango, F28:AI28, (COUNTIF(_xlpm.rango, "P") + COUNTIF(_xlpm.rango, "PF")) / (COUNTIF(_xlpm.rango, "P") + COUNTIF(_xlpm.rango, "A") + COUNTIF(_xlpm.rango, "PF"))) -> 1 | E28: =COUNTIF(F28:V28,"PF") -> 3 | H28: P | I28: pf | K28: PF | L28: PF | AS28: 46218 | AT28: Inicio Vacaciones de Invierno | AU28: MEC - VACACIONES
A29: 25 | B29: x | C29: =+'Datos '!B26 -> BRAHIAN JARA | D29: =_xlfn.LET(_xlpm.rango, F29:AI29, (COUNTIF(_xlpm.rango, "P") + COUNTIF(_xlpm.rango, "PF")) / (COUNTIF(_xlpm.rango, "P") + COUNTIF(_xlpm.rango, "A") + COUNTIF(_xlpm.rango, "PF"))) -> 1 | E29: =COUNTIF(F29:V29,"PF") -> 1 | F29: p | H29: p | J29: p | L29: PF | M29: p | O29: p | AS29: 46219 | AT29: Inicio Vacaciones de Invierno | AU29: MEC - VACACIONES
A30: 26 | B30: x | C30: =+'Datos '!B27 -> JOSIAS MARTINEZ | D30: =_xlfn.LET(_xlpm.rango, F30:AI30, (COUNTIF(_xlpm.rango, "P") + COUNTIF(_xlpm.rango, "PF")) / (COUNTIF(_xlpm.rango, "P") + COUNTIF(_xlpm.rango, "A") + COUNTIF(_xlpm.rango, "PF"))) -> 1 | E30: =COUNTIF(F30:V30,"PF") -> 2 | H30: PC | J30: PC | L30: PF | M30: PF | AS30: 46220 | AT30: Inicio Vacaciones de Invierno | AU30: MEC - VACACIONES
A31: 27 | B31: x | C31: =+'Datos '!B28 -> KARINA NOTARIO | D31: =_xlfn.LET(_xlpm.rango, F31:AI31, _xlpm.presentes, COUNTIF(_xlpm.rango, "P") + COUNTIF(_xlpm.rango, "PF") + COUNTIF(_xlpm.rango, "PFC"), _xlpm.total, _xlpm.presentes + COUNTIF(_xlpm.rango, "A"), _xlpm.presentes / _xlpm.total ) -> 1 | E31: =COUNTIF(F31:V31,"PF") -> 1 | H31: PFC | L31: PF | AS31: 46221 | AT31: Inicio Vacaciones de Invierno | AU31: MEC - VACACIONES
A32: 28 | B32: x | C32: =+'Datos '!B29 -> SAMIRA PARDO | D32: =_xlfn.LET(_xlpm.rango, F32:AI32, (COUNTIF(_xlpm.rango, "P") + COUNTIF(_xlpm.rango, "PF")) / (COUNTIF(_xlpm.rango, "P") + COUNTIF(_xlpm.rango, "A") + COUNTIF(_xlpm.rango, "PF"))) -> 0.66666667 | E32: =COUNTIF(F32:V32,"PF") -> 2 | K32: pfF | L32: PF | M32: PF | O32: a | AS32: 46222 | AT32: Inicio Vacaciones de Invierno | AU32: MEC - VACACIONES
A33: 29 | B33: x | C33: =+'Datos '!B30 -> JONATHAN PINHO | D33: =_xlfn.LET(_xlpm.rango, F33:AI33, (COUNTIF(_xlpm.rango, "P") + COUNTIF(_xlpm.rango, "PF")) / (COUNTIF(_xlpm.rango, "P") + COUNTIF(_xlpm.rango, "A") + COUNTIF(_xlpm.rango, "PF"))) -> 1 | E33: =COUNTIF(F33:V33,"PF") -> 3 | H33: P | K33: pf | L33: PF | M33: PF | AS33: 46223 | AT33: Inicio Vacaciones de Invierno | AU33: MEC - VACACIONES
A34: 30 | B34: XX | C34: =+'Datos '!B31 -> LUCERO QUIÑONEZ | D34: =_xlfn.LET(_xlpm.rango, F34:AI34, (COUNTIF(_xlpm.rango, "P") + COUNTIF(_xlpm.rango, "PF")) / (COUNTIF(_xlpm.rango, "P") + COUNTIF(_xlpm.rango, "A") + COUNTIF(_xlpm.rango, "PF"))) -> 0.5 | E34: =COUNTIF(F34:V34,"PF") -> 1 | L34: PF | O34: a | AS34: 46224 | AT34: Inicio Vacaciones de Invierno | AU34: MEC - VACACIONES
A35: 31 | B35: X | C35: =+'Datos '!B32 -> ALEXIS RECALDE | D35: =_xlfn.LET(_xlpm.rango, F35:AI35, (COUNTIF(_xlpm.rango, "P") + COUNTIF(_xlpm.rango, "PF")) / (COUNTIF(_xlpm.rango, "P") + COUNTIF(_xlpm.rango, "A") + COUNTIF(_xlpm.rango, "PF"))) -> 1 | E35: =COUNTIF(F35:V35,"PF") -> 0 | H35: p | J35: p | L35: p | AS35: 46225 | AT35: Inicio Vacaciones de Invierno | AU35: MEC - VACACIONES
A36: 32 | B36: x | C36: =+'Datos '!B33 -> VANIA ROA | D36: =_xlfn.LET(_xlpm.rango, F36:AI36, (COUNTIF(_xlpm.rango, "P") + COUNTIF(_xlpm.rango, "PF")) / (COUNTIF(_xlpm.rango, "P") + COUNTIF(_xlpm.rango, "A") + COUNTIF(_xlpm.rango, "PF"))) -> 1 | E36: =COUNTIF(F36:V36,"PF") -> 1 | H36: pf | J36: p | K36: pfc | L36: p | AS36: 46226 | AT36: Inicio Vacaciones de Invierno | AU36: MEC - VACACIONES
A37: 33 | B37: XX | C37: =+'Datos '!B34 -> JOSIAS ROLON | D37: =_xlfn.LET(_xlpm.rango, F37:AI37, (COUNTIF(_xlpm.rango, "P") + COUNTIF(_xlpm.rango, "PF")) / (COUNTIF(_xlpm.rango, "P") + COUNTIF(_xlpm.rango, "A") + COUNTIF(_xlpm.rango, "PF"))) -> 1 | E37: =COUNTIF(F37:V37,"PF") -> 1 | L37: PF | Q37: No presento su cuaderno | AS37: 46227 | AT37: Fin Vacaciones de Invierno | AU37: MEC - VACACIONES
A38: 34 | B38: x | C38: =+'Datos '!B35 -> HEIDY ROMERO | D38: =_xlfn.LET(_xlpm.rango, F38:AI38, (COUNTIF(_xlpm.rango, "P") + COUNTIF(_xlpm.rango, "PF")) / (COUNTIF(_xlpm.rango, "P") + COUNTIF(_xlpm.rango, "A") + COUNTIF(_xlpm.rango, "PF"))) -> 1 | E38: =COUNTIF(F38:V38,"PF") -> 4 | H38: PF | J38: PF | L38: PF | M38: PF | AS38: 46227 | AT38: Natalicio del Mcal. Francisco Solano López | AU38: Dia para conmemorar
A39: 35 | B39: x | C39: =+'Datos '!B36 -> LAURA ROUSSILLON | D39: =_xlfn.LET(_xlpm.rango, F31:AI31, _xlpm.presentes, COUNTIF(_xlpm.rango, "P") + COUNTIF(_xlpm.rango, "PF") + COUNTIF(_xlpm.rango, "PFC"), _xlpm.total, _xlpm.presentes + COUNTIF(_xlpm.rango, "A"), _xlpm.presentes / _xlpm.total ) -> 1 | E39: =COUNTIF(F39:V39,"PF") -> 2 | H39: PF | L39: PF | M39: PFC | AS39: 46233 | AT39: Día de la Amistad (Cruzada Mundial de la Amistad) | AU39: Dia para conmemorar
A40: 36 | B40: x | C40: =+'Datos '!B37 -> CHRISTOPHER SALCEDO | D40: =_xlfn.LET(_xlpm.rango, F40:AI40, (COUNTIF(_xlpm.rango, "P") + COUNTIF(_xlpm.rango, "PF")) / (COUNTIF(_xlpm.rango, "P") + COUNTIF(_xlpm.rango, "A") + COUNTIF(_xlpm.rango, "PF"))) -> #DIV/0! | E40: =COUNTIF(F40:V40,"PF") -> 0 | L40: PFC | M40: PFC | AS40: 46248 | AT40: Día de la Bandera | AU40: Dia para conmemorar
A41: 37 | B41: x | C41: =+'Datos '!B38 -> ALEX SAMANIEGO | D41: =_xlfn.LET(_xlpm.rango, F41:AI41, (COUNTIF(_xlpm.rango, "P") + COUNTIF(_xlpm.rango, "PF")) / (COUNTIF(_xlpm.rango, "P") + COUNTIF(_xlpm.rango, "A") + COUNTIF(_xlpm.rango, "PF"))) -> 1 | E41: =COUNTIF(F41:V41,"PF") -> 4 | H41: pf | J41: pf | K41: pf | L41: PF | M41: PFF | AS41: 46249 | AT41: Fundación de Asunción | AU41: Feriado Nacional
A42: 38 | B42: x | C42: =+'Datos '!B39 -> ROBERT SANCHEZ | D42: =_xlfn.LET(_xlpm.rango, F42:AI42, (COUNTIF(_xlpm.rango, "P") + COUNTIF(_xlpm.rango, "PF")) / (COUNTIF(_xlpm.rango, "P") + COUNTIF(_xlpm.rango, "A") + COUNTIF(_xlpm.rango, "PF"))) -> 1 | E42: =COUNTIF(F42:V42,"PF") -> 1 | H42: P | I42: P | J42: PF | M42: PFC | AS42: 46249 | AT42: Fundación de Asunción y Día del Niño (En Paraguay) | AU42: Dia para conmemorar
A43: 39 | B43: X | C43: =+'Datos '!B40 -> MARIA SANTA | D43: =_xlfn.LET(_xlpm.rango, F43:AI43, (COUNTIF(_xlpm.rango, "P") + COUNTIF(_xlpm.rango, "PF")) / (COUNTIF(_xlpm.rango, "P") + COUNTIF(_xlpm.rango, "A") + COUNTIF(_xlpm.rango, "PF"))) -> 0.14285714 | E43: =COUNTIF(F43:V43,"PF") -> 1 | F43: A | G43: A | H43: A | I43: Ausente | J43: A | K43: A | L43: PF | O43: a | AS43: 46250 | AT43: Día de los Niños Mártires de Acosta Ñu | AU43: Dia para conmemorar
A44: 40 | B44: x | C44: =+'Datos '!B41 -> FREDY SILVA | D44: =_xlfn.LET(_xlpm.rango, F44:AI44, (COUNTIF(_xlpm.rango, "P") + COUNTIF(_xlpm.rango, "PF")) / (COUNTIF(_xlpm.rango, "P") + COUNTIF(_xlpm.rango, "A") + COUNTIF(_xlpm.rango, "PF"))) -> #DIV/0! | E44: =COUNTIF(F44:V44,"PF") -> 0 | H44: PFC | J44: PFC | L44: PFC | M44: PFC | AS44: 46256 | AT44: Día del Folklore Paraguayo | AU44: Dia para conmemorar
A45: 41 | B45: x | C45: =+'Datos '!B42 -> LIZZIE VERA | D45: =_xlfn.LET(_xlpm.rango, F45:AI45, (COUNTIF(_xlpm.rango, "P") + COUNTIF(_xlpm.rango, "PF")) / (COUNTIF(_xlpm.rango, "P") + COUNTIF(_xlpm.rango, "A") + COUNTIF(_xlpm.rango, "PF"))) -> 1 | E45: =COUNTIF(F45:V45,"PF") -> 1 | H45: PF | J45: PFC | L45: PFC | M45: PFC | AS45: 46259 | AT45: Día del Idioma Guaraní | AU45: Dia para conmemorar
A46: 42 | B46: x | C46: =+'Datos '!B43 -> JONATHAN VILLASANTI | D46: =_xlfn.LET(_xlpm.rango, F46:AI46, (COUNTIF(_xlpm.rango, "P") + COUNTIF(_xlpm.rango, "PF")) / (COUNTIF(_xlpm.rango, "P") + COUNTIF(_xlpm.rango, "A") + COUNTIF(_xlpm.rango, "PF"))) -> 0.16666667 | E46: =COUNTIF(F46:V46,"PF") -> 1 | F46: A | G46: A | H46: A | I46: Ausente | J46: A | K46: A | L46: PF | AS46: 46286 | AT46: Día de la Juventud y de la Primavera | AU46: Clase Normal
A47: 43 | B47: X | C47: =+'Datos '!B44 -> THIAGO DUARTE | D47: =_xlfn.LET(_xlpm.rango, F47:AI47, (COUNTIF(_xlpm.rango, "P") + COUNTIF(_xlpm.rango, "PF")) / (COUNTIF(_xlpm.rango, "P") + COUNTIF(_xlpm.rango, "A") + COUNTIF(_xlpm.rango, "PF"))) -> 1 | E47: =COUNTIF(F47:V47,"PF") -> 3 | H47: PF | L47: PF | M47: PF | AS47: 46287 | AT47: Día de la Juventud y de la Primavera | AU47: Clase Normal
H48: Moral Social | J48: La responsabilidad | L48: Elabora un mapa mental de Moral Social ( Trabajo remitido por WS) | AS48: 46294 | AT48: Batalla de Boquerón (Victoria paraguaya, 1932) | AU48: Dia para conmemorar
H49: PF | I49: Presente y Firma - trabajo completo | AS49: 46307 | AT49: Día de la Raza (Descubrimiento de América) | AU49: Dia para conmemorar
H50: PPC | I50: Presente, falta completar | AS50: 46318 | AT50: Día del Diseñador Gráfico y del Radiooperador | AU50: Dia para conmemorar
H51: P | I51: Presente | AS51: 46351 | AT51: Día Internacional de la Eliminación de la Violencia contra la Mujer | AU51: Dia para conmemorar
H52: A | I52: Ausente | AS52: 46356 | AT52: Finalización de Clases | AU52: MEC - CIERRE PEDAGOGICAS
J53: PFC | L53: PFC | AS53: 46364 | AT53: Día de la Virgen de Caacupé | AU53: Feriado Nacional
AS54: 46367 | AT54: Cierre de Actividades Administrativas | AU54: MEC - CIERRE ADM.
AS55: 46381 | AT55: Navidad | AU55: Feriado Nacional

Sheet 04-RSA
A2: ID | B2: Nombre del Alumno | C2: - Identifica principios éticos y morales. | D2: - Diferencia moral y moralidad. | E2: - Reconoce problemáticas éticas globales. | F2: - Analiza causas de la mortalidad infantil. | G2: - Valora el código de convivencia. | H2: - Propone normas de respeto mutuo. | I2: - Define tipos de bullying. | J2: - Identifica consecuencias psicológicas. | K2: - Propone acciones de prevención. | L2: - Diferencia mediación de negociación. | M2: - Aplica pasos de la negociación asertiva. | N2: - Define el concepto de canasta básica. | O2: - Analiza el impacto de la pobreza. | P2: - Identifica tipos de violencia familiar. | Q2: - Conoce rutas de denuncia en Paraguay. | R2: - Explica la universalidad de los derechos. | S2: - Distingue progresividad de irreversibilidad. | T2: - Reconoce formas de explotación infantil. | U2: - Valora la protección contra el trabajo forzado. | V2: - Identifica factores de exclusión femenina. | W2: - Propone acciones para la igualdad. | X2: - Identifica la función tributaria. | Y2: - Valora la función social de los tributos. | Z2: - Reconoce funciones del Ministerio de Hacienda. | AA2: - Diferencia roles de Intendentes y Gobernadores.
A3: 1 | B3: =+'03-ASISTENCIA'!C4 -> Apellido/s Nombre/s
A4: 2 | B4: =+'03-ASISTENCIA'!C5 -> NAHIARA ARCE
A5: 3 | B5: =+'03-ASISTENCIA'!C6 -> GUADALUPE ARCE
A6: 4 | B6: =+'03-ASISTENCIA'!C7 -> ALMA AYALA
A7: 5 | B7: =+'03-ASISTENCIA'!C8 -> GUADALUPE BARRETO
A8: 6 | B8: =+'03-ASISTENCIA'!C9 -> LUIS BARRIOS
A9: 7 | B9: =+'03-ASISTENCIA'!C10 -> LUANA BENITEZ
A10: 8 | B10: =+'03-ASISTENCIA'!C11 -> CARLOS CABALLERO
A11: 9 | B11: =+'03-ASISTENCIA'!C12 -> THAIS CACERES
A12: 10 | B12: =+'03-ASISTENCIA'!C13 -> MAXIMO DIAZ
A13: 11 | B13: =+'03-ASISTENCIA'!C14 -> BASTTIAN ESTIGARRIBIA
A14: 12 | B14: =+'03-ASISTENCIA'!C15 -> IVONNE FERNANDEZ
... A23: 21 | B23: =+'03-ASISTENCIA'!C24 -> SANTIAGO GIMENEZ

Sheet 05-BD- CUADRO ANECDOTICO
A1: Registro de Alumnos
B2: Fecha | C2: Alumno | D2: Situación | E2: Categoria | F2: Tipo de Indicador
B3: 46146 | C3: LAUTARO GARCIA | D3: Ale-40. Ejerce presión negativa o bullying. | E3: =+VLOOKUP(D3,indicadores,3,0) -> Alerta/Mejora | F3: =+VLOOKUP(D3,indicadores,4,0) -> Socio-Emocional
F4: =+VLOOKUP(D4,indicadores,4,0) -> #N/A
F5: =+VLOOKUP(D5,indicadores,4,0) -> #N/A
F6: =+VLOOKUP(D6,indicadores,4,0) -> #N/A
F7: =+VLOOKUP(D7,indicadores,4,0) -> #N/A
F8: =+VLOOKUP(D8,indicadores,4,0) -> #N/A
F9: =+VLOOKUP(D9,indicadores,4,0) -> #N/A
F10: =+VLOOKUP(D10,indicadores,4,0) -> #N/A
F11: =+VLOOKUP(D11,indicadores,4,0) -> #N/A
F12: =+VLOOKUP(D12,indicadores,4,0) -> #N/A

Sheet 05-RESUMEN -CUADRO ANECDOTICO
B3: Etiquetas de fila | C3: Cantidad de Reportes | E3: . | F3: .
B4: Alerta/Mejora | C4: 1 | E4: Etiquetas de fila | F4: Alerta/Mejora | G4: Total general
B5: Total general | C5: 1 | E5: Nombre y Apellido | F5: 1 | G5: 1
E6: Total general | F6: 1 | G6: 1
B8: Etiquetas de fila | C8: Tipo de Indicador.
B9: Total general
I12: 46136

Sheet 06-PROCESO
C2: PLANILLA DE ASISTENCIA | D2: =+AVERAGE(D5:D24) -> 0.99 | N2: SEPTIMO | R2: TT | S2: 2026
A4: N° Orden | C4: Apellido/s Nombre/s | D4: % DE ASISTENCIA | E4: FIRMAS | F4: =+'04-RSA'!C2 -> - Identifica principios éticos y morales. | G4: =+'04-RSA'!D2 -> - Diferencia moral y moralidad. | H4: =+'04-RSA'!E2 -> - Reconoce problemáticas éticas globales. | I4: =+'04-RSA'!F2 -> - Analiza causas de la mortalidad infantil. | J4: =+'04-RSA'!G2 -> - Valora el código de convivencia. | K4: =+'04-RSA'!H2 -> - Propone normas de respeto mutuo. | L4: =+'04-RSA'!J2 -> - Identifica consecuencias psicológicas. | M4: =+'04-RSA'!K2 -> - Propone acciones de prevención. | N4: =+'04-RSA'!L2 -> - Diferencia mediación de negociación. | O4: =+'04-RSA'!M2 -> - Aplica pasos de la negociación asertiva. | P4: =+'04-RSA'!N2 -> - Define el concepto de canasta básica. | Q4: =+'04-RSA'!O2 -> - Analiza el impacto de la pobreza. | R4: =+'04-RSA'!P2 -> - Identifica tipos de violencia familiar. | S4: =+'04-RSA'!Q2 -> - Conoce rutas de denuncia en Paraguay. | ... V4: =+'04-RSA'!T2 -> - Reconoce formas de explotación infantil. | W4: =+'04-RSA'!V2 -> - Identifica factores de exclusión femenina. | X4: =+'04-RSA'!W2 -> - Propone acciones para la igualdad. | Y4: =+'04-RSA'!X2 -> - Identifica la función tributaria. | Z4: =+'04-RSA'!Y2 -> - Valora la función social de los tributos. | AA4: =+'04-RSA'!Z2 -> - Reconoce funciones del Ministerio de Hacienda. | AB4: =+'04-RSA'!AA2 -> - Diferencia roles de Intendentes y Gobernadores. | AC4: =+'04-RSA'!AB2 -> 0 | AD4: =+'04-RSA'!AC2 -> 0 | ... AH4: =+'04-RSA'!AG2 -> 0 | EL4: =+TODAY() -> 46146
A5: 1 | C5: =+'Datos '!B2 -> NAHIARA ARCE | D5: =+'03-ASISTENCIA'!D5 -> 1 | E5: =+'03-ASISTENCIA'!E5 -> 2 | F5: =+'04-RSA'!C4 -> 0 | G5: =+'04-RSA'!D4 -> 0 | H5: =+'04-RSA'!E4 -> 0 | I5: =+'04-RSA'!F4 -> 0 | J5: =+'04-RSA'!G4 -> 0 | K5: =+'04-RSA'!H4 -> 0 | L5: =+'04-RSA'!J4 -> 0 | M5: =+'04-RSA'!K4 -> 0 | N5: =+'04-RSA'!L4 -> 0 | O5: =+'04-RSA'!M4 -> 0 | P5: =+'04-RSA'!N4 -> 0 | Q5: =+'04-RSA'!O4 -> 0 | R5: =+'04-RSA'!P4 -> 0 | S5: =+'04-RSA'!Q4 -> 0 | ... V5: =+'04-RSA'!T4 -> 0
A6: 2 | C6: =+'Datos '!B3 -> GUADALUPE ARCE | D6: =+'03-ASISTENCIA'!D6 -> 0.8 | E6: =+'03-ASISTENCIA'!E6 -> 3 | F6: =+'04-RSA'!C5 -> 0 | G6: =+'04-RSA'!D5 -> 0 | H6: =+'04-RSA'!E5 -> 0 | I6: =+'04-RSA'!F5 -> 0 | J6: =+'04-RSA'!G5 -> 0 | K6: =+'04-RSA'!H5 -> 0 | L6: =+'04-RSA'!J5 -> 0 | M6: =+'04-RSA'!K5 -> 0 | N6: =+'04-RSA'!L5 -> 0 | O6: =+'04-RSA'!M5 -> 0 | P6: =+'04-RSA'!N5 -> 0 | Q6: =+'04-RSA'!O5 -> 0 | R6: =+'04-RSA'!P5 -> 0 | S6: =+'04-RSA'!Q5 -> 0 | ... V6: =+'04-RSA'!T5 -> 0
A7: 3 | C7: =+'Datos '!B4 -> ALMA AYALA | D7: =+'03-ASISTENCIA'!D7 -> 1 | E7: =+'03-ASISTENCIA'!E7 -> 4 | F7: =+'04-RSA'!C6 -> 0 | G7: =+'04-RSA'!D6 -> 0 | H7: =+'04-RSA'!E6 -> 0 | I7: =+'04-RSA'!F6 -> 0 | J7: =+'04-RSA'!G6 -> 0 | K7: =+'04-RSA'!H6 -> 0 | L7: =+'04-RSA'!J6 -> 0 | M7: =+'04-RSA'!K6 -> 0 | N7: =+'04-RSA'!L6 -> 0 | O7: =+'04-RSA'!M6 -> 0 | P7: =+'04-RSA'!N6 -> 0 | Q7: =+'04-RSA'!O6 -> 0 | R7: =+'04-RSA'!P6 -> 0 | S7: =+'04-RSA'!Q6 -> 0 | ... V7: =+'04-RSA'!T6 -> 0
A8: 4 | C8: =+'Datos '!B5 -> GUADALUPE BARRETO | D8: =+'03-ASISTENCIA'!D8 -> 1 | E8: =+'03-ASISTENCIA'!E8 -> 3 | F8: =+'04-RSA'!C7 -> 0 | G8: =+'04-RSA'!D7 -> 0 | H8: =+'04-RSA'!E7 -> 0 | I8: =+'04-RSA'!F7 -> 0 | J8: =+'04-RSA'!G7 -> 0 | K8: =+'04-RSA'!H7 -> 0 | L8: =+'04-RSA'!J7 -> 0 | M8: =+'04-RSA'!K7 -> 0 | N8: =+'04-RSA'!L7 -> 0 | O8: =+'04-RSA'!M7 -> 0 | P8: =+'04-RSA'!N7 -> 0 | Q8: =+'04-RSA'!O7 -> 0 | R8: =+'04-RSA'!P7 -> 0 | S8: =+'04-RSA'!Q7 -> 0 | ... V8: =+'04-RSA'!T7 -> 0
A9: 5 | C9: =+'Datos '!B6 -> LUIS BARRIOS | D9: =+'03-ASISTENCIA'!D9 -> 1 | E9: =+'03-ASISTENCIA'!E9 -> 4 | F9: =+'04-RSA'!C8 -> 0 | G9: =+'04-RSA'!D8 -> 0 | H9: =+'04-RSA'!E8 -> 0 | I9: =+'04-RSA'!F8 -> 0 | J9: =+'04-RSA'!G8 -> 0 | K9: =+'04-RSA'!H8 -> 0 | L9: =+'04-RSA'!J8 -> 0 | M9: =+'04-RSA'!K8 -> 0 | N9: =+'04-RSA'!L8 -> 0 | O9: =+'04-RSA'!M8 -> 0 | P9: =+'04-RSA'!N8 -> 0 | Q9: =+'04-RSA'!O8 -> 0 | R9: =+'04-RSA'!P8 -> 0 | S9: =+'04-RSA'!Q8 -> 0 | ... V9: =+'04-RSA'!T8 -> 0
A10: 6 | C10: =+'Datos '!B7 -> LUANA BENITEZ | D10: =+'03-ASISTENCIA'!D10 -> 1 | E10: =+'03-ASISTENCIA'!E10 -> 3 | F10: =+'04-RSA'!C9 -> 0 | G10: =+'04-RSA'!D9 -> 0 | H10: =+'04-RSA'!E9 -> 0 | I10: =+'04-RSA'!F9 -> 0 | J10: =+'04-RSA'!G9 -> 0 | K10: =+'04-RSA'!H9 -> 0 | L10: =+'04-RSA'!J9 -> 0 | M10: =+'04-RSA'!K9 -> 0 | N10: =+'04-RSA'!L9 -> 0 | O10: =+'04-RSA'!M9 -> 0 | P10: =+'04-RSA'!N9 -> 0 | Q10: =+'04-RSA'!O9 -> 0 | R10: =+'04-RSA'!P9 -> 0 | S10: =+'04-RSA'!Q9 -> 0 | ... V10: =+'04-RSA'!T9 -> 0
A11: 7 | C11: =+'Datos '!B8 -> CARLOS CABALLERO | D11: =+'03-ASISTENCIA'!D11 -> 1 | E11: =+'03-ASISTENCIA'!E11 -> 2 | F11: =+'04-RSA'!C10 -> 0 | G11: =+'04-RSA'!D10 -> 0 | H11: =+'04-RSA'!E10 -> 0 | I11: =+'04-RSA'!F10 -> 0 | J11: =+'04-RSA'!G10 -> 0 | K11: =+'04-RSA'!H10 -> 0 | L11: =+'04-RSA'!J10 -> 0 | M11: =+'04-RSA'!K10 -> 0 | N11: =+'04-RSA'!L10 -> 0 | O11: =+'04-RSA'!M10 -> 0 | P11: =+'04-RSA'!N10 -> 0 | Q11: =+'04-RSA'!O10 -> 0 | R11: =+'04-RSA'!P10 -> 0 | S11: =+'04-RSA'!Q10 -> 0 | ... V11: =+'04-RSA'!T10 -> 0
A12: 8 | C12: =+'Datos '!B9 -> THAIS CACERES | D12: =+'03-ASISTENCIA'!D12 -> 1 | E12: =+'03-ASISTENCIA'!E12 -> 3 | F12: =+'04-RSA'!C11 -> 0 | G12: =+'04-RSA'!D11 -> 0 | H12: =+'04-RSA'!E11 -> 0 | I12: =+'04-RSA'!F11 -> 0 | J12: =+'04-RSA'!G11 -> 0 | K12: =+'04-RSA'!H11 -> 0 | L12: =+'04-RSA'!J11 -> 0 | M12: =+'04-RSA'!K11 -> 0 | N12: =+'04-RSA'!L11 -> 0 | O12: =+'04-RSA'!M11 -> 0 | P12: =+'04-RSA'!N11 -> 0 | Q12: =+'04-RSA'!O11 -> 0 | R12: =+'04-RSA'!P11 -> 0 | S12: =+'04-RSA'!Q11 -> 0 | ... V12: =+'04-RSA'!T11 -> 0
A13: 9 | B13: D | C13: =+'Datos '!B10 -> MAXIMO DIAZ | D13: =+'03-ASISTENCIA'!D13 -> 1 | E13: =+'03-ASISTENCIA'!E13 -> 2 | F13: =+'04-RSA'!C12 -> 0 | G13: =+'04-RSA'!D12 -> 0 | H13: =+'04-RSA'!E12 -> 0 | I13: =+'04-RSA'!F12 -> 0 | J13: =+'04-RSA'!G12 -> 0 | K13: =+'04-RSA'!H12 -> 0 | L13: =+'04-RSA'!J12 -> 0 | M13: =+'04-RSA'!K12 -> 0 | N13: =+'04-RSA'!L12 -> 0 | O13: =+'04-RSA'!M12 -> 0 | P13: =+'04-RSA'!N12 -> 0 | Q13: =+'04-RSA'!O12 -> 0 | R13: =+'04-RSA'!P12 -> 0 | S13: =+'04-RSA'!Q12 -> 0 | ... V13: =+'04-RSA'!T12 -> 0
A14: 10 | C14: =+'Datos '!B11 -> BASTTIAN ESTIGARRIBIA | D14: =+'03-ASISTENCIA'!D14 -> 1 | E14: =+'03-ASISTENCIA'!E14 -> 4 | F14: =+'04-RSA'!C13 -> 0 | G14: =+'04-RSA'!D13 -> 0 | H14: =+'04-RSA'!E13 -> 0 | I14: =+'04-RSA'!F13 -> 0 | J14: =+'04-RSA'!G13 -> 0 | K14: =+'04-RSA'!H13 -> 0 | L14: =+'04-RSA'!J13 -> 0 | M14: =+'04-RSA'!K13 -> 0 | N14: =+'04-RSA'!L13 -> 0 | O14: =+'04-RSA'!M13 -> 0 | P14: =+'04-RSA'!N13 -> 0 | Q14: =+'04-RSA'!O13 -> 0 | R14: =+'04-RSA'!P13 -> 0 | S14: =+'04-RSA'!Q13 -> 0 | ... V14: =+'04-RSA'!T13 -> 0
A15: 11 | C15: =+'Datos '!B12 -> IVONNE FERNANDEZ | D15: =+'03-ASISTENCIA'!D15 -> 1 | E15: =+'03-ASISTENCIA'!E15 -> 4 | F15: =+'04-RSA'!C14 -> 0 | G15: =+'04-RSA'!D14 -> 0 | H15: =+'04-RSA'!E14 -> 0 | I15: =+'04-RSA'!F14 -> 0 | J15: =+'04-RSA'!G14 -> 0 | K15: =+'04-RSA'!H14 -> 0 | L15: =+'04-RSA'!J14 -> 0 | M15: =+'04-RSA'!K14 -> 0 | N15: =+'04-RSA'!L14 -> 0 | O15: =+'04-RSA'!M14 -> 0 | P15: =+'04-RSA'!N14 -> 0 | Q15: =+'04-RSA'!O14 -> 0 | R15: =+'04-RSA'!P14 -> 0 | S15: =+'04-RSA'!Q14 -> 0 | ... V15: =+'04-RSA'!T14 -> 0
A16: 12 | C16: =+'Datos '!B13 -> EMILIA FERNANDEZ | D16: =+'03-ASISTENCIA'!D16 -> 1 | E16: =+'03-ASISTENCIA'!E16 -> 2 | F16: =+'04-RSA'!C15 -> 0 | G16: =+'04-RSA'!D15 -> 0 | H16: =+'04-RSA'!E15 -> 0 | I16: =+'04-RSA'!F15 -> 0 | J16: =+'04-RSA'!G15 -> 0 | K16: =+'04-RSA'!H15 -> 0 | L16: =+'04-RSA'!J15 -> 0 | M16: =+'04-RSA'!K15 -> 0 | N16: =+'04-RSA'!L15 -> 0 | O16: =+'04-RSA'!M15 -> 0 | P16: =+'04-RSA'!N15 -> 0 | Q16: =+'04-RSA'!O15 -> 0 | R16: =+'04-RSA'!P15 -> 0 | S16: =+'04-RSA'!Q15 -> 0 | ... V16: =+'04-RSA'!T15 -> 0
A17: 13 | C17: =+'Datos '!B14 -> TAMARA FLORENTIN | D17: =+'03-ASISTENCIA'!D17 -> 1 | E17: =+'03-ASISTENCIA'!E17 -> 3 | F17: =+'04-RSA'!C16 -> 0 | G17: =+'04-RSA'!D16 -> 0 | H17: =+'04-RSA'!E16 -> 0 | I17: =+'04-RSA'!F16 -> 0 | J17: =+'04-RSA'!G16 -> 0 | K17: =+'04-RSA'!H16 -> 0 | L17: =+'04-RSA'!J16 -> 0 | M17: =+'04-RSA'!K16 -> 0 | N17: =+'04-RSA'!L16 -> 0 | O17: =+'04-RSA'!M16 -> 0 | P17: =+'04-RSA'!N16 -> 0 | Q17: =+'04-RSA'!O16 -> 0 | R17: =+'04-RSA'!P16 -> 0 | S17: =+'04-RSA'!Q16 -> 0 | ... V17: =+'04-RSA'!T16 -> 0
A18: 14 | C18: =+'Datos '!B15 -> AYLEN FLORENTIN | D18: =+'03-ASISTENCIA'!D18 -> 1 | E18: =+'03-ASISTENCIA'!E18 -> 4 | F18: =+'04-RSA'!C17 -> 0 | G18: =+'04-RSA'!D17 -> 0 | H18: =+'04-RSA'!E17 -> 0 | I18: =+'04-RSA'!F17 -> 0 | J18: =+'04-RSA'!G17 -> 0 | K18: =+'04-RSA'!H17 -> 0 | L18: =+'04-RSA'!J17 -> 0 | M18: =+'04-RSA'!K17 -> 0 | N18: =+'04-RSA'!L17 -> 0 | O18: =+'04-RSA'!M17 -> 0 | P18: =+'04-RSA'!N17 -> 0 | Q18: =+'04-RSA'!O17 -> 0 | R18: =+'04-RSA'!P17 -> 0 | S18: =+'04-RSA'!Q17 -> 0 | ... V18: =+'04-RSA'!T17 -> 0
A19: 15 | C19: =+'Datos '!B16 -> PAULA FRANCO | D19: =+'03-ASISTENCIA'!D19 -> 1 | E19: =+'03-ASISTENCIA'!E19 -> 3 | F19: =+'04-RSA'!C18 -> 0 | G19: =+'04-RSA'!D18 -> 0 | H19: =+'04-RSA'!E18 -> 0 | I19: =+'04-RSA'!F18 -> 0 | J19: =+'04-RSA'!G18 -> 0 | K19: =+'04-RSA'!H18 -> 0 | L19: =+'04-RSA'!J18 -> 0 | M19: =+'04-RSA'!K18 -> 0 | N19: =+'04-RSA'!L18 -> 0 | O19: =+'04-RSA'!M18 -> 0 | P19: =+'04-RSA'!N18 -> 0 | Q19: =+'04-RSA'!O18 -> 0 | R19: =+'04-RSA'!P18 -> 0 | S19: =+'04-RSA'!Q18 -> 0 | ... V19: =+'04-RSA'!T18 -> 0
A20: 16 | C20: =+'Datos '!B17 -> JEANELLY GAONA | D20: =+'03-ASISTENCIA'!D20 -> 1 | E20: =+'03-ASISTENCIA'!E20 -> 3 | F20: =+'04-RSA'!C19 -> 0 | G20: =+'04-RSA'!D19 -> 0 | H20: =+'04-RSA'!E19 -> 0 | I20: =+'04-RSA'!F19 -> 0 | J20: =+'04-RSA'!G19 -> 0 | K20: =+'04-RSA'!H19 -> 0 | L20: =+'04-RSA'!J19 -> 0 | M20: =+'04-RSA'!K19 -> 0 | N20: =+'04-RSA'!L19 -> 0 | O20: =+'04-RSA'!M19 -> 0 | P20: =+'04-RSA'!N19 -> 0 | Q20: =+'04-RSA'!O19 -> 0 | R20: =+'04-RSA'!P19 -> 0 | S20: =+'04-RSA'!Q19 -> 0 | ... V20: =+'04-RSA'!T19 -> 0
A21: 17 | C21: =+'Datos '!B18 -> LUANA GAONA | D21: =+'03-ASISTENCIA'!D21 -> 1 | E21: =+'03-ASISTENCIA'!E21 -> 3 | F21: =+'04-RSA'!C20 -> 0 | G21: =+'04-RSA'!D20 -> 0 | H21: =+'04-RSA'!E20 -> 0 | I21: =+'04-RSA'!F20 -> 0 | J21: =+'04-RSA'!G20 -> 0 | K21: =+'04-RSA'!H20 -> 0 | L21: =+'04-RSA'!J20 -> 0 | M21: =+'04-RSA'!K20 -> 0 | N21: =+'04-RSA'!L20 -> 0 | O21: =+'04-RSA'!M20 -> 0 | P21: =+'04-RSA'!N20 -> 0 | Q21: =+'04-RSA'!O20 -> 0 | R21: =+'04-RSA'!P20 -> 0 | S21: =+'04-RSA'!Q20 -> 0 | ... V21: =+'04-RSA'!T20 -> 0
A22: 18 | C22: =+'Datos '!B19 -> ABIGAIL GARCIA | D22: =+'03-ASISTENCIA'!D22 -> 1 | E22: =+'03-ASISTENCIA'!E22 -> 3 | F22: =+'04-RSA'!C21 -> 0 | G22: =+'04-RSA'!D21 -> 0 | H22: =+'04-RSA'!E21 -> 0 | I22: =+'04-RSA'!F21 -> 0 | J22: =+'04-RSA'!G21 -> 0 | K22: =+'04-RSA'!H21 -> 0 | L22: =+'04-RSA'!J21 -> 0 | M22: =+'04-RSA'!K21 -> 0 | N22: =+'04-RSA'!L21 -> 0 | O22: =+'04-RSA'!M21 -> 0 | P22: =+'04-RSA'!N21 -> 0 | Q22: =+'04-RSA'!O21 -> 0 | R22: =+'04-RSA'!P21 -> 0 | S22: =+'04-RSA'!Q21 -> 0 | ... V22: =+'04-RSA'!T21 -> 0
A23: 19 | C23: =+'Datos '!B20 -> LAUTARO GARCIA | D23: =+'03-ASISTENCIA'!D23 -> 1 | E23: =+'03-ASISTENCIA'!E23 -> 2 | F23: =+'04-RSA'!C22 -> 0 | G23: =+'04-RSA'!D22 -> 0 | H23: =+'04-RSA'!E22 -> 0 | I23: =+'04-RSA'!F22 -> 0 | J23: =+'04-RSA'!G22 -> 0 | K23: =+'04-RSA'!H22 -> 0 | L23: =+'04-RSA'!J22 -> 0 | M23: =+'04-RSA'!K22 -> 0 | N23: =+'04-RSA'!L22 -> 0 | O23: =+'04-RSA'!M22 -> 0 | P23: =+'04-RSA'!N22 -> 0 | Q23: =+'04-RSA'!O22 -> 0 | R23: =+'04-RSA'!P22 -> 0 | S23: =+'04-RSA'!Q22 -> 0 | ... V23: =+'04-RSA'!T22 -> 0
A24: 20 | C24: =+'Datos '!B21 -> SANTIAGO GIMENEZ | D24: =+'03-ASISTENCIA'!D24 -> 1 | E24: =+'03-ASISTENCIA'!E24 -> 3 | F24: =+'04-RSA'!C23 -> 0 | G24: =+'04-RSA'!D23 -> 0 | H24: =+'04-RSA'!E23 -> 0 | I24: =+'04-RSA'!F23 -> 0 | J24: =+'04-RSA'!G23 -> 0 | K24: =+'04-RSA'!H23 -> 0 | L24: =+'04-RSA'!J23 -> 0 | M24: =+'04-RSA'!K23 -> 0 | N24: =+'04-RSA'!L23 -> 0 | O24: =+'04-RSA'!M23 -> 0 | P24: =+'04-RSA'!N23 -> 0 | Q24: =+'04-RSA'!O23 -> 0 | R24: =+'04-RSA'!P23 -> 0 | S24: =+'04-RSA'!Q23 -> 0 | ... V24: =+'04-RSA'!T23 -> 0

Sheet 07-CALENDARIO MEC
A1: Fecha (DD/MM/YYYY) | B1: Evento / Conmemoración | C1: Tipo
A2: 46023 | B2: Año Nuevo | C2: Feriado Nacional
A3: 46063 | B3: Apertura Institucional y Retorno Docente | C3: MEC - INSTITUCIONAL
A4: 46076 | B4: Inicio de Clases (Sector Oficial) | C4: MEC - INSTITUCIONAL
A5: 46077 | B5: Día de la Mujer Paraguaya (Homenaje a las Residentas) | C5: Dia para conmemorar
A6: 46082 | B6: Día de los Héroes | C6: Feriado Nacional
A7: 46082 | B7: Día de los Héroes (Muerte del Mcal. López en Cerro Corá) | C7: Dia para conmemorar
A8: 46102 | B8: Día Mundial de la Poesía y Día del Síndrome de Down | C8: Dia para conmemorar
A9: 46114 | B9: Jueves Santo (Receso) | C9: Feriado Nacional
A10: 46115 | B10: Viernes Santo (Receso) | C10: Feriado Nacional
A11: 46135 | B11: Día del Libro y del Derecho de Autor | C11: Dia para conmemorar
A12: 46138 | B12: Día del Periodista (Muerte de Santiago Leguizamón) | C12: Dia para conmemorar
A13: 46142 | B13: Día del Maestro (En Paraguay) | C13: Dia para conmemorar
... A52: 46381 | B52: Navidad | C52: Feriado Nacional

Sheet 08- INDICADORES AC
B1: Indicador | C1: Indicador | D1: Tipo de Indicador | E1: Categoría
B2: =+CONCATENATE(LEFT(D2,3),"-",C2) -> Ale-02. Presenta lagunas en conocimientos previos. | C2: 02. Presenta lagunas en conocimientos previos. | D2: Alerta/Mejora | E2: Académica
B3: =+CONCATENATE(LEFT(D3,3),"-",C3) -> Ale-04. Se limita a memorizar sin comprender. | C3: 04. Se limita a memorizar sin comprender. | D3: Alerta/Mejora | E3: Académica
B4: =+CONCATENATE(LEFT(D4,3),"-",C4) -> Ale-06. Entrega tareas incompletas o descuidadas. | C4: 06. Entrega tareas incompletas o descuidadas. | D4: Alerta/Mejora | E4: Académica
B5: =+CONCATENATE(LEFT(D5,3),"-",C5) -> Ale-08. Se bloquea ante desafíos matemáticos. | C5: 08. Se bloquea ante desafíos matemáticos. | D5: Alerta/Mejora | E5: Académica
B6: =+CONCATENATE(LEFT(D6,3),"-",C6) -> Ale-10. Tiene dificultades de expresión oral/escrita. | C6: 10. Tiene dificultades de expresión oral/escrita. | D6: Alerta/Mejora | E6: Académica
B7: =+CONCATENATE(LEFT(D7,3),"-",C7) -> Ale-12. Muestra rechazo o desinterés por la lectura. | C7: 12. Muestra rechazo o desinterés por la lectura. | D7: Alerta/Mejora | E7: Académica
B8: =+CONCATENATE(LEFT(D8,3),"-",C8) -> Ale-14. Requiere supervisión constante para avanzar. | C8: 14. Requiere supervisión constante para avanzar. | D8: Alerta/Mejora | E8: Académica
B9: =+CONCATENATE(LEFT(D9,3),"-",C9) -> Ale-16. Muestra apatía por temas nuevos. | C9: 16. Muestra apatía por temas nuevos. | D9: Alerta/Mejora | E9: Académica
B10: =+CONCATENATE(LEFT(D10,3),"-",C10) -> Ale-18. Desafía activamente la autoridad. | C10: 18. Desafía activamente la autoridad. | D10: Alerta/Mejora | E10: Conductual
B11: =+CONCATENATE(LEFT(D11,3),"-",C11) -> Ale-20. Presenta retardos o inasistencias frecuentes. | C11: 20. Presenta retardos o inasistencias frecuentes. | D11: Alerta/Mejora | E11: Conductual
B12: =+CONCATENATE(LEFT(D12,3),"-",C12) -> Ale-22. Daña el mobiliario o materiales escolares. | C12: 22. Daña el mobiliario o materiales escolares. | D12: Alerta/Mejora | E12: Conductual
B13: =+CONCATENATE(LEFT(D13,3),"-",C13) -> Ale-24. Interrumpe constantemente el flujo de clase. | C13: 24. Interrumpe constantemente el flujo de clase. | D13: Alerta/Mejora | E13: Conductual
... B52: =+CONCATENATE(LEFT(D52,3),"-",C52) -> For-49. Acepta retroalimentación constructiva. | C52: 49. Acepta retroalimentación constructiva. | D52: Fortaleza/Logro | E52: Actitudinal

Sheet 09.Diagnostico
A1: Categoría | B1: Indicador | C1: Indicador | D1: Tipo de Indicador | E1: Cantidad de veces | F1: NOTA | G1: =+'Datos '!G37 -> 37
A2: Académica | B2: =+CONCATENATE(LEFT(D2,3),"-",C2) -> Ale-02. Presenta lagunas en conocimientos previos. | C2: 02. Presenta lagunas en conocimientos previos. | D2: Alerta/Mejora | E2: 37 | F2: =IF(D2="Alerta/Mejora", IF(E2<=3, 5, IF(E2<=7, 4, IF(E2<=11, 3, IF(E2<=15, 2, 1)))), IF(E2>=34, 5, IF(E2>=30, 4, IF(E2>=26, 3, IF(E2>=22, 2, 1)))) ) -> 1 | G2: =+G$1-E2 -> 0
A3: Académica | B3: =+CONCATENATE(LEFT(D3,3),"-",C3) -> Ale-04. Se limita a memorizar sin comprender. | C3: 04. Se limita a memorizar sin comprender. | D3: Alerta/Mejora | E3: =37-19 -> 18 | F3: =IF(D3="Alerta/Mejora", IF(E3<=3, 5, IF(E3<=7, 4, IF(E3<=11, 3, IF(E3<=15, 2, 1)))), IF(E3>=34, 5, IF(E3>=30, 4, IF(E3>=26, 3, IF(E3>=22, 2, 1)))) ) -> 1 | G3: =+G$1-E3 -> 19 | I3: 0 | J3: 21 | K3: 1 | M3: Promedio de Cantidad de veces | N3: Etiquetas de columna
A4: Académica | B4: =+CONCATENATE(LEFT(D4,3),"-",C4) -> Ale-06. Entrega tareas incompletas o descuidadas. | C4: 06. Entrega tareas incompletas o descuidadas. | D4: Alerta/Mejora | E4: 4 | F4: =IF(D4="Alerta/Mejora", IF(E4<=3, 5, IF(E4<=7, 4, IF(E4<=11, 3, IF(E4<=15, 2, 1)))), IF(E4>=34, 5, IF(E4>=30, 4, IF(E4>=26, 3, IF(E4>=22, 2, 1)))) ) -> 4 | G4: =+G$1-E4 -> 33 | I4: 22 | J4: 25 | K4: 2 | M4: Etiquetas de fila | N4: Alerta/Mejora | O4: Fortaleza/Logro | P4: Total general
A5: Académica | B5: =+CONCATENATE(LEFT(D5,3),"-",C5) -> Ale-08. Se bloquea ante desafíos matemáticos. | C5: 08. Se bloquea ante desafíos matemáticos. | D5: Alerta/Mejora | E5: 18 | F5: =IF(D5="Alerta/Mejora", IF(E5<=3, 5, IF(E5<=7, 4, IF(E5<=11, 3, IF(E5<=15, 2, 1)))), IF(E5>=34, 5, IF(E5>=30, 4, IF(E5>=26, 3, IF(E5>=22, 2, 1)))) ) -> 1 | G5: =+G$1-E5 -> 19 | I5: 26 | J5: 29 | K5: 3 | M5: Académica | N5: 3.5 | O5: 11.25 | P5: 7.375
A6: Académica | B6: =+CONCATENATE(LEFT(D6,3),"-",C6) -> Ale-10. Tiene dificultades de expresión oral/escrita. | C6: 10. Tiene dificultades de expresión oral/escrita. | D6: Alerta/Mejora | E6: 14 | F6: =IF(D6="Alerta/Mejora", IF(E6<=3, 5, IF(E6<=7, 4, IF(E6<=11, 3, IF(E6<=15, 2, 1)))), IF(E6>=34, 5, IF(E6>=30, 4, IF(E6>=26, 3, IF(E6>=22, 2, 1)))) ) -> 2 | G6: =+G$1-E6 -> 23 | I6: 30 | J6: 33 | K6: 4 | M6: Actitudinal | N6: 2.6666667 | O6: 32.333333 | P6: 17.5
A7: Académica | B7: =+CONCATENATE(LEFT(D7,3),"-",C7) -> Ale-12. Muestra rechazo o desinterés por la lectura. | C7: 12. Muestra rechazo o desinterés por la lectura. | D7: Alerta/Mejora | E7: 11 | F7: =IF(D7="Alerta/Mejora", IF(E7<=3, 5, IF(E7<=7, 4, IF(E7<=11, 3, IF(E7<=15, 2, 1)))), IF(E7>=34, 5, IF(E7>=30, 4, IF(E7>=26, 3, IF(E7>=22, 2, 1)))) ) -> 3 | G7: =+G$1-E7 -> 26 | I7: 34 | J7: 37 | K7: 5 | M7: Conductual | N7: 4.125 | O7: 29.875 | P7: 17
A8: Académica | B8: =+CONCATENATE(LEFT(D8,3),"-",C8) -> Ale-14. Requiere supervisión constante para avanzar. | C8: 14. Requiere supervisión constante para avanzar. | D8: Alerta/Mejora | E8: =37-18 -> 19 | F8: =IF(D8="Alerta/Mejora", IF(E8<=3, 5, IF(E8<=7, 4, IF(E8<=11, 3, IF(E8<=15, 2, 1)))), IF(E8>=34, 5, IF(E8>=30, 4, IF(E8>=26, 3, IF(E8>=22, 2, 1)))) ) -> 1 | G8: =+G$1-E8 -> 18 | M8: Socio-Emocional | N8: 3.3333333 | O8: 27 | P8: 15.166667
A9: Académica | B9: =+CONCATENATE(LEFT(D9,3),"-",C9) -> Ale-16. Muestra apatía por temas nuevos. | C9: 16. Muestra apatía por temas nuevos. | D9: Alerta/Mejora | E9: 7 | F9: =IF(D9="Alerta/Mejora", IF(E9<=3, 5, IF(E9<=7, 4, IF(E9<=11, 3, IF(E9<=15, 2, 1)))), IF(E9>=34, 5, IF(E9>=30, 4, IF(E9>=26, 3, IF(E9>=22, 2, 1)))) ) -> 4 | G9: =+G$1-E9 -> 30 | M9: Total general | N9: 3.56 | O9: 23.52 | P9: 13.54
A10: Conductual | B10: =+CONCATENATE(LEFT(D10,3),"-",C10) -> Ale-18. Desafía activamente la autoridad. | C10: 18. Desafía activamente la autoridad. | D10: Alerta/Mejora | E10: 16 | F10: =IF(D10="Alerta/Mejora", IF(E10<=3, 5, IF(E10<=7, 4, IF(E10<=11, 3, IF(E10<=15, 2, 1)))), IF(E10>=34, 5, IF(E10>=30, 4, IF(E10>=26, 3, IF(E10>=22, 2, 1)))) ) -> 1 | G10: =+G$1-E10 -> 21
A11: Conductual | B11: =+CONCATENATE(LEFT(D11,3),"-",C11) -> Ale-20. Presenta retardos o inasistencias frecuentes. | C11: 20. Presenta retardos o inasistencias frecuentes. | D11: Alerta/Mejora | E11: 2 | F11: =IF(D11="Alerta/Mejora", IF(E11<=3, 5, IF(E11<=7, 4, IF(E11<=11, 3, IF(E11<=15, 2, 1)))), IF(E11>=34, 5, IF(E11>=30, 4, IF(E11>=26, 3, IF(E11>=22, 2, 1)))) ) -> 5 | G11: =+G$1-E11 -> 35
A12: Conductual | B12: =+CONCATENATE(LEFT(D12,3),"-",C12) -> Ale-22. Daña el mobiliario o materiales escolares. | C12: 22. Daña el mobiliario o materiales escolares. | D12: Alerta/Mejora | E12: 1 | F12: =IF(D12="Alerta/Mejora", IF(E12<=3, 5, IF(E12<=7, 4, IF(E12<=11, 3, IF(E12<=15, 2, 1)))), IF(E12>=34, 5, IF(E12>=30, 4, IF(E12>=26, 3, IF(E12>=22, 2, 1)))) ) -> 5 | G12: =+G$1-E12 -> 36
A13: Conductual | B13: =+CONCATENATE(LEFT(D13,3),"-",C13) -> Ale-24. Interrumpe constantemente el flujo de clase. | C13: 24. Interrumpe constantemente el flujo de clase. | D13: Alerta/Mejora | E13: 2 | F13: =IF(D13="Alerta/Mejora", IF(E13<=3, 5, IF(E13<=7, 4, IF(E13<=11, 3, IF(E13<=15, 2, 1)))), IF(E13>=34, 5, IF(E13>=30, 4, IF(E13>=26, 3, IF(E13>=22, 2, 1)))) ) -> 5 | G13: =+G$1-E13 -> 35
A14: Conductual | B14: =+CONCATENATE(LEFT(D14,3),"-",C14) -> Ale-26. Emplea lenguaje soez o despectivo. | C14: 26. Emplea lenguaje soez o despectivo. | D14: Alerta/Mejora | E14: 11 | F14: =IF(D14="Alerta/Mejora", IF(E14<=3, 5, IF(E14<=7, 4, IF(E14<=11, 3, IF(E14<=15, 2, 1)))), IF(E14>=34, 5, IF(E14>=30, 4, IF(E14>=26, 3, IF(E14>=22, 2, 1)))) ) -> 3 | G14: =+G$1-E14 -> 26
A15: Conductual | B15: =+CONCATENATE(LEFT(D15,3),"-",C15) -> Ale-28. Miente o culpa a otros por sus actos. | C15: 28. Miente o culpa a otros por sus actos. | D15: Alerta/Mejora | E15: 19 | F15: =IF(D15="Alerta/Mejora", IF(E15<=3, 5, IF(E15<=7, 4, IF(E15<=11, 3, IF(E15<=15, 2, 1)))), IF(E15>=34, 5, IF(E15>=30, 4, IF(E15>=26, 3, IF(E15>=22, 2, 1)))) ) -> 1 | G15: =+G$1-E15 -> 18
A16: Conductual | B16: =+CONCATENATE(LEFT(D16,3),"-",C16) -> Ale-30. Se distrae con dispositivos electrónicos. | C16: 30. Se distrae con dispositivos electrónicos. | D16: Alerta/Mejora | E16: 16 | F16: =IF(D16="Alerta/Mejora", IF(E16<=3, 5, IF(E16<=7, 4, IF(E16<=11, 3, IF(E16<=15, 2, 1)))), IF(E16>=34, 5, IF(E16>=30, 4, IF(E16>=26, 3, IF(E16>=22, 2, 1)))) ) -> 1 | G16: =+G$1-E16 -> 21
A17: Conductual | B17: =+CONCATENATE(LEFT(D17,3),"-",C17) -> Ale-32. Fomenta el desorden o el caos en el grupo. | C17: 32. Fomenta el desorden o el caos en el grupo. | D17: Alerta/Mejora | E17: 6 | F17: =IF(D17="Alerta/Mejora", IF(E17<=3, 5, IF(E17<=7, 4, IF(E17<=11, 3, IF(E17<=15, 2, 1)))), IF(E17>=34, 5, IF(E17>=30, 4, IF(E17>=26, 3, IF(E17>=22, 2, 1)))) ) -> 4 | G17: =+G$1-E17 -> 31
A18: Socio-Emocional | B18: =+CONCATENATE(LEFT(D18,3),"-",C18) -> Ale-34. Se rinde fácilmente ante la frustración. | C18: 34. Se rinde fácilmente ante la frustración. | D18: Alerta/Mejora | E18: 19 | F18: =IF(D18="Alerta/Mejora", IF(E18<=3, 5, IF(E18<=7, 4, IF(E18<=11, 3, IF(E18<=15, 2, 1)))), IF(E18>=34, 5, IF(E18>=30, 4, IF(E18>=26, 3, IF(E18>=22, 2, 1)))) ) -> 1 | G18: =+G$1-E18 -> 18
A19: Socio-Emocional | B19: =+CONCATENATE(LEFT(D19,3),"-",C19) -> Ale-36. Trabaja de forma aislada o es individualista. | C19: 36. Trabaja de forma aislada o es individualista. | D19: Alerta/Mejora | E19: 14 | F19: =IF(D19="Alerta/Mejora", IF(E19<=3, 5, IF(E19<=7, 4, IF(E19<=11, 3, IF(E19<=15, 2, 1)))), IF(E19>=34, 5, IF(E19>=30, 4, IF(E19>=26, 3, IF(E19>=22, 2, 1)))) ) -> 2 | G19: =+G$1-E19 -> 23
A20: Socio-Emocional | B20: =+CONCATENATE(LEFT(D20,3),"-",C20) -> Ale-38. Ignora o se burla de los sentimientos de otros. | C20: 38. Ignora o se burla de los sentimientos de otros. | D20: Alerta/Mejora | E20: 15 | F20: =IF(D20="Alerta/Mejora", IF(E20<=3, 5, IF(E20<=7, 4, IF(E20<=11, 3, IF(E20<=15, 2, 1)))), IF(E20>=34, 5, IF(E20>=30, 4, IF(E20>=26, 3, IF(E20>=22, 2, 1)))) ) -> 2 | G20: =+G$1-E20 -> 22
A21: Socio-Emocional | B21: =+CONCATENATE(LEFT(D21,3),"-",C21) -> Ale-40. Ejerce presión negativa o bullying. | C21: 40. Ejerce presión negativa o bullying. | D21: Alerta/Mejora | E21: 4 | F21: =IF(D21="Alerta/Mejora", IF(E21<=3, 5, IF(E21<=7, 4, IF(E21<=11, 3, IF(E21<=15, 2, 1)))), IF(E21>=34, 5, IF(E21>=30, 4, IF(E21>=26, 3, IF(E21>=22, 2, 1)))) ) -> 4 | G21: =+G$1-E21 -> 33
... A26: Actitudinal | B26: =+CONCATENATE(LEFT(D26,3),"-",C26) -> Ale-50. Se muestra a la defensiva ante críticas. | C26: 50. Se muestra a la defensiva ante críticas. | D26: Alerta/Mejora | E26: 11 | F26: =IF(D26="Alerta/Mejora", IF(E26<=3, 5, IF(E26<=7, 4, IF(E26<=11, 3, IF(E26<=15, 2, 1)))), IF(E26>=34, 5, IF(E26>=30, 4, IF(E26>=26, 3, IF(E26>=22, 2, 1)))) ) -> 3 | G26: =+G$1-E26 -> 26
A28: Académica | B28: =+CONCATENATE(LEFT(D28,3),"-",C28) -> For-01. Domina los conceptos clave del grado. | C28: 01. Domina los conceptos clave del grado. | D28: Fortaleza/Logro | E28: 6 | F28: =IF(D28="Alerta/Mejora", IF(E28<=3, 5, IF(E28<=7, 4, IF(E28<=11, 3, IF(E28<=15, 2, 1)))), IF(E28>=34, 5, IF(E28>=30, 4, IF(E28>=26, 3, IF(E28>=22, 2, 1)))) ) -> 1 | G28: =+E28 -> 6
A29: Académica | B29: =+CONCATENATE(LEFT(D29,3),"-",C29) -> For-03. Posee un pensamiento crítico y analítico. | C29: 03. Posee un pensamiento crítico y analítico. | D29: Fortaleza/Logro | E29: 11 | F29: =IF(D29="Alerta/Mejora", IF(E29<=3, 5, IF(E29<=7, 4, IF(E29<=11, 3, IF(E29<=15, 2, 1)))), IF(E29>=34, 5, IF(E29>=30, 4, IF(E29>=26, 3, IF(E29>=22, 2, 1)))) ) -> 1 | G29: =+E29 -> 11
A30: Académica | B30: =+CONCATENATE(LEFT(D30,3),"-",C30) -> For-05. Entrega trabajos con alta calidad y orden. | C30: 05. Entrega trabajos con alta calidad y orden. | D30: Fortaleza/Logro | E30: 12 | F30: =IF(D30="Alerta/Mejora", IF(E30<=3, 5, IF(E30<=7, 4, IF(E30<=11, 3, IF(E30<=15, 2, 1)))), IF(E30>=34, 5, IF(E30>=30, 4, IF(E30>=26, 3, IF(E30>=22, 2, 1)))) ) -> 1 | G30: =+E30 -> 12
A31: Académica | B31: =+CONCATENATE(LEFT(D31,3),"-",C31) -> For-07. Resuelve problemas lógicos con fluidez. | C31: 07. Resuelve problemas lógicos con fluidez. | D31: Fortaleza/Logro | E31: 11 | F31: =IF(D31="Alerta/Mejora", IF(E31<=3, 5, IF(E31<=7, 4, IF(E31<=11, 3, IF(E31<=15, 2, 1)))), IF(E31>=34, 5, IF(E31>=30, 4, IF(E31>=26, 3, IF(E31>=22, 2, 1)))) ) -> 1 | G31: =+E31 -> 11
A32: Académica | B32: =+CONCATENATE(LEFT(D32,3),"-",C32) -> For-09. Utiliza vocabulario técnico preciso. | C32: 09. Utiliza vocabulario técnico preciso. | D32: Fortaleza/Logro | E32: 10 | F32: =IF(D32="Alerta/Mejora", IF(E32<=3, 5, IF(E32<=7, 4, IF(E32<=11, 3, IF(E32<=15, 2, 1)))), IF(E32>=34, 5, IF(E32>=30, 4, IF(E32>=26, 3, IF(E32>=22, 2, 1)))) ) -> 1 | G32: =+E32 -> 10
A33: Académica | B33: =+CONCATENATE(LEFT(D33,3),"-",C33) -> For-11. Posee excelentes hábitos de lectura. | C33: 11. Posee excelentes hábitos de lectura. | D33: Fortaleza/Logro | E33: 10 | F33: =IF(D33="Alerta/Mejora", IF(E33<=3, 5, IF(E33<=7, 4, IF(E33<=11, 3, IF(E33<=15, 2, 1)))), IF(E33>=34, 5, IF(E33>=30, 4, IF(E33>=26, 3, IF(E33>=22, 2, 1)))) ) -> 1 | G33: =+E33 -> 10
A34: Académica | B34: =+CONCATENATE(LEFT(D34,3),"-",C34) -> For-13. Es autónomo en la realización de tareas. | C34: 13. Es autónomo en la realización de tareas. | D34: Fortaleza/Logro | E34: 12 | F34: =IF(D34="Alerta/Mejora", IF(E34<=3, 5, IF(E34<=7, 4, IF(E34<=11, 3, IF(E34<=15, 2, 1)))), IF(E34>=34, 5, IF(E34>=30, 4, IF(E34>=26, 3, IF(E34>=22, 2, 1)))) ) -> 1 | G34: =+E34 -> 12
A35: Académica | B35: =+CONCATENATE(LEFT(D35,3),"-",C35) -> For-15. Investiga más allá de lo solicitado. | C35: 15. Investiga más allá de lo solicitado. | D35: Fortaleza/Logro | E35: 13 | F35: =IF(D35="Alerta/Mejora", IF(E35<=3, 5, IF(E35<=7, 4, IF(E35<=11, 3, IF(E35<=15, 2, 1)))), IF(E35>=34, 5, IF(E35>=30, 4, IF(E35>=26, 3, IF(E35>=22, 2, 1)))) ) -> 1 | G35: =+E35 -> 13
A36: Conductual | B36: =+CONCATENATE(LEFT(D36,3),"-",C36) -> For-17. Respeta las normas de convivencia. | C36: 17. Respeta las normas de convivencia. | D36: Fortaleza/Logro | E36: 22 | F36: =IF(D36="Alerta/Mejora", IF(E36<=3, 5, IF(E36<=7, 4, IF(E36<=11, 3, IF(E36<=15, 2, 1)))), IF(E36>=34, 5, IF(E36>=30, 4, IF(E36>=26, 3, IF(E36>=22, 2, 1)))) ) -> 2 | G36: =+E36 -> 22
A37: Conductual | B37: =+CONCATENATE(LEFT(D37,3),"-",C37) -> For-19. Es puntual en todas sus obligaciones. | C37: 19. Es puntual en todas sus obligaciones. | D37: Fortaleza/Logro | E37: 10 | F37: =IF(D37="Alerta/Mejora", IF(E37<=3, 5, IF(E37<=7, 4, IF(E37<=11, 3, IF(E37<=15, 2, 1)))), IF(E37>=34, 5, IF(E37>=30, 4, IF(E37>=26, 3, IF(E37>=22, 2, 1)))) ) -> 1 | G37: =+E37 -> 10
A38: Conductual | B38: =+CONCATENATE(LEFT(D38,3),"-",C38) -> For-21. Cuida el material propio y ajeno. | C38: 21. Cuida el material propio y ajeno. | D38: Fortaleza/Logro | E38: 23 | F38: =IF(D38="Alerta/Mejora", IF(E38<=3, 5, IF(E38<=7, 4, IF(E38<=11, 3, IF(E38<=15, 2, 1)))), IF(E38>=34, 5, IF(E38>=30, 4, IF(E38>=26, 3, IF(E38>=22, 2, 1)))) ) -> 2 | G38: =+E38 -> 23
A39: Conductual | B39: =+CONCATENATE(LEFT(D39,3),"-",C39) -> For-23. Escucha con atención y no interrumpe. | C39: 23. Escucha con atención y no interrumpe. | D39: Fortaleza/Logro | E39: 20 | F39: =IF(D39="Alerta/Mejora", IF(E39<=3, 5, IF(E39<=7, 4, IF(E39<=11, 3, IF(E39<=15, 2, 1)))), IF(E39>=34, 5, IF(E39>=30, 4, IF(E39>=26, 3, IF(E39>=22, 2, 1)))) ) -> 1 | G39: =+E39 -> 20
A40: Conductual | B40: =+CONCATENATE(LEFT(D40,3),"-",C40) -> For-25. Utiliza el lenguaje de forma respetuosa. | C40: 25. Utiliza el lenguaje de forma respetuosa. | D40: Fortaleza/Logro | E40: 13 | F40: =IF(D40="Alerta/Mejora", IF(E40<=3, 5, IF(E40<=7, 4, IF(E40<=11, 3, IF(E40<=15, 2, 1)))), IF(E40>=34, 5, IF(E40>=30, 4, IF(E40>=26, 3, IF(E40>=22, 2, 1)))) ) -> 1 | G40: =+E40 -> 13
A41: Conductual | B41: =+CONCATENATE(LEFT(D41,3),"-",C41) -> For-27. Reconoce sus errores honestamente. | C41: 27. Reconoce sus errores honestamente. | D41: Fortaleza/Logro | E41: 15 | F41: =IF(D41="Alerta/Mejora", IF(E41<=3, 5, IF(E41<=7, 4, IF(E41<=11, 3, IF(E41<=15, 2, 1)))), IF(E41>=34, 5, IF(E41>=30, 4, IF(E41>=26, 3, IF(E41>=22, 2, 1)))) ) -> 1 | G41: =+E41 -> 15 | K41: Suma de Cantidad de veces | L41: Etiquetas de columna
A42: Conductual | B42: =+CONCATENATE(LEFT(D42,3),"-",C42) -> For-29. Usa la tecnología con fines educativos. | C42: 29. Usa la tecnología con fines educativos. | D42: Fortaleza/Logro | E42: 3 | F42: =IF(D42="Alerta/Mejora", IF(E42<=3, 5, IF(E42<=7, 4, IF(E42<=11, 3, IF(E42<=15, 2, 1)))), IF(E42>=34, 5, IF(E42>=30, 4, IF(E42>=26, 3, IF(E42>=22, 2, 1)))) ) -> 1 | G42: =+E42 -> 3 | K42: Etiquetas de fila | L42: Alerta/Mejora | M42: Fortaleza/Logro | N42: Total general
A43: Conductual | B43: =+CONCATENATE(LEFT(D43,3),"-",C43) -> For-31. Mantiene el orden en espacios comunes. | C43: 31. Mantiene el orden en espacios comunes. | D43: Fortaleza/Logro | E43: 11 | F43: =IF(D43="Alerta/Mejora", IF(E43<=3, 5, IF(E43<=7, 4, IF(E43<=11, 3, IF(E43<=15, 2, 1)))), IF(E43>=34, 5, IF(E43>=30, 4, IF(E43>=26, 3, IF(E43>=22, 2, 1)))) ) -> 1 | G43: =+E43 -> 11 | K43: Académica | L43: 28 | M43: 90 | N43: 118
A44: Socio-Emocional | B44: =+CONCATENATE(LEFT(D44,3),"-",C44) -> For-33. Muestra resiliencia ante el fracaso. | C44: 33. Muestra resiliencia ante el fracaso. | D44: Fortaleza/Logro | E44: 18 | F44: =IF(D44="Alerta/Mejora", IF(E44<=3, 5, IF(E44<=7, 4, IF(E44<=11, 3, IF(E44<=15, 2, 1)))), IF(E44>=34, 5, IF(E44>=30, 4, IF(E44>=26, 3, IF(E44>=22, 2, 1)))) ) -> 1 | G44: =+E44 -> 18 | K44: Actitudinal | L44: 8 | M44: 97 | N44: 105
A45: Socio-Emocional | B45: =+CONCATENATE(LEFT(D45,3),"-",C45) -> For-35. Trabaja de forma colaborativa y equitativa. | C45: 35. Trabaja de forma colaborativa y equitativa. | D45: Fortaleza/Logro | E45: 16 | F45: =IF(D45="Alerta/Mejora", IF(E45<=3, 5, IF(E45<=7, 4, IF(E45<=11, 3, IF(E45<=15, 2, 1)))), IF(E45>=34, 5, IF(E45>=30, 4, IF(E45>=26, 3, IF(E45>=22, 2, 1)))) ) -> 1 | G45: =+E45 -> 16 | K45: Conductual | L45: 33 | M45: 239 | N45: 272
A46: Socio-Emocional | B46: =+CONCATENATE(LEFT(D46,3),"-",C46) -> For-37. Es empático con las necesidades ajenas. | C46: 37. Es empático con las necesidades ajenas. | D46: Fortaleza/Logro | E46: 18 | F46: =IF(D46="Alerta/Mejora", IF(E46<=3, 5, IF(E46<=7, 4, IF(E46<=11, 3, IF(E46<=15, 2, 1)))), IF(E46>=34, 5, IF(E46>=30, 4, IF(E46>=26, 3, IF(E46>=22, 2, 1)))) ) -> 1 | G46: =+E46 -> 18 | K46: Socio-Emocional | L46: 20 | M46: 162 | N46: 182
A47: Socio-Emocional | B47: =+CONCATENATE(LEFT(D47,3),"-",C47) -> For-39. Posee un liderazgo positivo y ético. | C47: 39. Posee un liderazgo positivo y ético. | D47: Fortaleza/Logro | E47: 4 | F47: =IF(D47="Alerta/Mejora", IF(E47<=3, 5, IF(E47<=7, 4, IF(E47<=11, 3, IF(E47<=15, 2, 1)))), IF(E47>=34, 5, IF(E47>=30, 4, IF(E47>=26, 3, IF(E47>=22, 2, 1)))) ) -> 1 | G47: =+E47 -> 4 | K47: Total general | L47: 89 | M47: 588 | N47: 677
A48: Socio-Emocional | B48: =+CONCATENATE(LEFT(D48,3),"-",C48) -> For-41. Se comunica de manera asertiva. | C48: 41. Se comunica de manera asertiva. | D48: Fortaleza/Logro | E48: 6 | F48: =IF(D48="Alerta/Mejora", IF(E48<=3, 5, IF(E48<=7, 4, IF(E48<=11, 3, IF(E48<=15, 2, 1)))), IF(E48>=34, 5, IF(E48>=30, 4, IF(E48>=26, 3, IF(E48>=22, 2, 1)))) ) -> 1 | G48: =+E48 -> 6
A49: Socio-Emocional | B49: =+CONCATENATE(LEFT(D49,3),"-",C49) -> For-43. Tiene una autoestima académica sólida. | C49: 43. Tiene una autoestima académica sólida. | D49: Fortaleza/Logro | E49: 6 | F49: =IF(D49="Alerta/Mejora", IF(E49<=3, 5, IF(E49<=7, 4, IF(E49<=11, 3, IF(E49<=15, 2, 1)))), IF(E49>=34, 5, IF(E49>=30, 4, IF(E49>=26, 3, IF(E49>=22, 2, 1)))) ) -> 1 | G49: =+E49 -> 6 | L49: Etiquetas de columna
A50: Actitudinal | B50: =+CONCATENATE(LEFT(D50,3),"-",C50) -> For-45. Muestra curiosidad e iniciativa propia. | C50: 45. Muestra curiosidad e iniciativa propia. | D50: Fortaleza/Logro | E50: 16 | F50: =IF(D50="Alerta/Mejora", IF(E50<=3, 5, IF(E50<=7, 4, IF(E50<=11, 3, IF(E50<=15, 2, 1)))), IF(E50>=34, 5, IF(E50>=30, 4, IF(E50>=26, 3, IF(E50>=22, 2, 1)))) ) -> 1 | G50: =+E50 -> 16 | L50: Alerta/Mejora | M50: Fortaleza/Logro | N50: (en blanco) | O50: Total general
A51: Actitudinal | B51: =+CONCATENATE(LEFT(D51,3),"-",C51) -> For-47. Es persistente en tareas complejas. | C51: 47. Es persistente en tareas complejas. | D51: Fortaleza/Logro | E51: 5 | F51: =IF(D51="Alerta/Mejora", IF(E51<=3, 5, IF(E51<=7, 4, IF(E51<=11, 3, IF(E51<=15, 2, 1)))), IF(E51>=34, 5, IF(E51>=30, 4, IF(E51>=26, 3, IF(E51>=22, 2, 1)))) ) -> 1 | G51: =+E51 -> 5 | K51: Suma de Cantidad de veces | L51: 89 | M51: 588 | O51: 677
A52: Actitudinal | B52: =+CONCATENATE(LEFT(D52,3),"-",C52) -> For-49. Acepta retroalimentación constructiva. | C52: 49. Acepta retroalimentación constructiva. | D52: Fortaleza/Logro | E52: 12 | F52: =IF(D52="Alerta/Mejora", IF(E52<=3, 5, IF(E52<=7, 4, IF(E52<=11, 3, IF(E52<=15, 2, 1)))), IF(E52>=34, 5, IF(E52>=30, 4, IF(E52>=26, 3, IF(E52>=22, 2, 1)))) ) -> 1 | G52: =+E52 -> 12
K55: Nota | L55: Cantidad de alumnos | N55: % de Alumnos
K56: 1 | L56: =ROUND((COUNTIF($F$2:$F$52, K56) / 50) * 37, 0) -> 25 | N56: =+L56/L$61 -> 0.67567568 | P56: Muy bueno | Q56: =+L60+L59 -> 5 | R56: =+Q56/L$61 -> 0.13513514
K57: 2 | L57: =ROUND((COUNTIF($F$2:$F$52, K57) / 50) * 37, 0) -> 4 | N57: =+L57/L$61 -> 0.10810811 | P57: Bueno | Q57: =+L58 -> 3 | R57: =+Q57/L$61 -> 0.081081081
K58: 3 | L58: =ROUND((COUNTIF($F$2:$F$52, K58) / 50) * 37, 0) -> 3 | N58: =+L58/L$61 -> 0.081081081 | P58: A mejorar | Q58: =+L56+L57 -> 29 | R58: =+Q58/L$61 -> 0.78378378
K59: 4 | L59: =ROUND((COUNTIF($F$2:$F$52, K59) / 50) * 37, 0) -> 3 | N59: =+L59/L$61 -> 0.081081081
K60: 5 | L60: =ROUND((COUNTIF($F$2:$F$52, K60) / 50) * 37, 0) -> 2 | N60: =+L60/L$61 -> 0.054054054
L61: =SUM(L56:L60) -> 37

Sheet Escala 
A1: COLEGIO SAGRADA FAMILIA
A2: ESCALA DE CALIFICACIONES - 60%
A4: 15 Puntos | B4: 16 Puntos | C4: 17 Puntos | D4: 18 Puntos | E4: 19 Puntos | F4: 20 Puntos | G4: 21 Puntos | H4: 22 Puntos
A5: 0 - 9 = 1 | B5: 0 - 9 = 1 | C5: 0 - 10 = 1 | D5: 0 - 10 = 1 | E5: 0 - 10 = 1 | F5: 0 - 11 = 1 | G5: 0 - 12 = 1 | H5: 0 - 13 = 1
A6: 9 - 10 = 2 | B6: 9 - 10 = 2 | C6: 11 - 12 = 2 | D6: 11 - 12 = 2 | E6: 11 - 12 = 2 | F6: 12 - 13 = 2 | G6: 13 - 14 = 2 | H6: 14 - 15 = 2
A7: 11 - 12 = 3 | B7: 11 - 12 = 3 | C7: 13 - 14 = 3 | D7: 13 - 14 = 3 | E7: 13 - 15 = 3 | F7: 14 - 16 = 3 | G7: 15 - 17 = 3 | H7: 16 - 18 = 3
A8: 13 - 14 = 4 | B8: 13 - 14 = 4 | C8: 15 - 16 = 4 | D8: 15 - 16 = 4 | E8: 16 - 17 = 4 | F8: 17 - 18 = 4 | G8: 18 - 19 = 4 | H8: 19 - 20 = 4
A9: 15 = 5 | B9: 15 - 16 = 5 | C9: 17 = 5 | D9: 17 - 18 = 5 | E9: 18 - 19 = 5 | F9: 19 - 20 = 5 | G9: 20 - 21 = 5 | H9: 21 - 22 = 5
A11: 23 Puntos | B11: 24 Puntos | C11: 25 Puntos | D11: 26 Puntos | E11: 27 Puntos | F11: 28 Puntos | G11: 29 Puntos | H11: 30 Puntos
A12: 0 - 13 = 1 | B12: 0 - 13 = 1 | C12: 0 - 14 = 1 | D12: 0 - 15 = 1 | E12: 0 - 15 = 1 | F12: 0 - 16 = 1 | G12: 0 - 17 = 1 | H12: 0 - 17 = 1
A13: 14 - 15 = 2 | B13: 14 - 16 = 2 | C13: 15 - 17 = 2 | D13: 16 - 18 = 2 | E13: 16 - 18 = 2 | F13: 17 - 19 = 2 | G13: 18 - 20 = 2 | H13: 18 - 20 = 2
A14: 16 - 18 = 3 | B14: 17 - 19 = 3 | C14: 18 - 20 = 3 | D14: 19 - 21 = 3 | E14: 19 - 21 = 3 | F14: 20 - 22 = 3 | G14: 21 - 23 = 3 | H14: 21 - 24 = 3
A15: 19 - 21 = 4 | B15: 20 - 22 = 4 | C15: 21 - 23 = 4 | D15: 22 - 24 = 4 | E15: 22 - 24 = 4 | F15: 23 - 25 = 4 | G15: 24 - 26 = 4 | H15: 25 - 27 = 4
A16: 22 - 23 = 5 | B16: 23 - 24 = 5 | C16: 24 - 25 = 5 | D16: 25 - 26 = 5 | E16: 25 - 27 = 5 | F16: 26 - 28 = 5 | G16: 27 - 29 = 5 | H16: 28 - 30 = 5
... A51: 58 - 63 = 5 | B51: 59 - 64 = 5 | C51: 60 - 65 = 5 | D51: 61 - 66 = 5 | E51: 61 - 67 = 5 | F51: 62 - 68 = 5 | G51: 63 - 69 = 5 | H51: 64 - 70 = 5
A56: COLEGIO SAGRADA FAMILIA
A57: ESCALA DE CALIFICACIONES - 60%
A59: 71 Puntos | B59: 72 Puntos | C59: 73 Puntos | D59: 74 Puntos | E59: 75 Puntos | F59: 76 Puntos | G59: 77 Puntos | H59: 78 Puntos
A60: 0 - 42 = 1 | B60: 0 - 42 = 1 | C60: 0 - 43 = 1 | D60: 0 - 43 = 1 | E60: 0 - 44 = 1 | F60: 0 - 45 = 1 | G60: 0 - 45 = 1 | H60: 0 - 46 = 1
A61: 43 - 49 = 2 | B61: 43 - 49 = 2 | C61: 44 - 50 = 2 | D61: 44 - 51 = 2 | E61: 45 - 52 = 2 | F61: 46 - 53 = 2 | G61: 46 - 53 = 2 | H61: 47 - 54 = 2
A62: 50 - 57 = 3 | B62: 50 - 57 = 3 | C62: 51 - 58 = 3 | D62: 52 - 59 = 3 | E62: 53 - 60 = 3 | F62: 54 - 61 = 3 | G62: 54 - 61 = 3 | H62: 55 - 62 = 3
A63: 58 - 64 = 4 | B63: 58 - 65 = 4 | C63: 59 - 66 = 4 | D63: 60 - 67 = 4 | E63: 61 - 68 = 4 | F63: 62 - 69 = 4 | G63: 62 - 69 = 4 | H63: 63 - 70 = 4
A64: 65 - 71 = 5 | B64: 66 - 72 = 5 | C64: 67 - 73 = 5 | D64: 68 - 74 = 5 | E64: 69 - 75 = 5 | F64: 70 - 76 = 5 | G64: 70 - 77 = 5 | H64: 71 - 78 = 5
A66: 79 Puntos | B66: 80 Puntos | C66: 81 Puntos | D66: 82 Puntos | E66: 83 Puntos | F66: 84 Puntos | G66: 85 Puntos | H66: 86 Puntos
A67: 0 - 46 = 1 | B67: 0 - 47 = 1 | C67: 0 - 48 = 1 | D67: 0 - 48 = 1 | E67: 0 - 48 = 1 | F67: 0 - 49 = 1 | G67: 0 - 50 = 1 | H67: 0 - 51 = 1
A68: 47 - 54 = 2 | B68: 48 - 55 = 2 | C68: 49 - 56 = 2 | D68: 49 - 56 = 2 | E68: 49 - 57 = 2 | F68: 50 - 58 = 2 | G68: 51 - 59 = 2 | H68: 52 - 60 = 2
A69: 55 - 63 = 3 | B69: 56 - 64 = 3 | C69: 57 - 65 = 3 | D69: 57 - 65 = 3 | E69: 58 - 66 = 3 | F69: 59 - 67 = 3 | G69: 60 - 68 = 3 | H69: 61 - 69 = 3
A70: 64 - 71 = 4 | B70: 65 - 72 = 4 | C70: 66 - 73 = 4 | D70: 66 - 74 = 4 | E70: 67 - 75 = 4 | F70: 68 - 76 = 4 | G70: 69 - 77 = 4 | H70: 70 - 78 = 4
A71: 72 - 79 = 5 | B71: 73 - 80 = 5 | C71: 74 - 81 = 5 | D71: 75 - 82 = 5 | E71: 76 - 83 = 5 | F71: 77 - 84 = 5 | G71: 78 - 85 = 5 | H71: 79 - 86 = 5
... A106: 108-119= 5 | B106: 109-120= 5 | C106: 110-121= 5 | D106: 111-122= 5 | E106: 112-123= 5 | F106: 113-124= 5 | G106: 114-125= 5 | H106: 115-126= 5

Sheet Datos 
A1: Nombre completo | B1: Nombre y Apellido | G1: 1 | H1: ARCE VILLALBA, DIDIER EMMANUEL
A2: ARCE CABALLERO, NAHIARA NAOMI | B2: =IFERROR(TRIM(LEFT(MID(A2, FIND(",", A2) + 1, LEN(A2)), FIND(" ", TRIM(MID(A2, FIND(",", A2) + 1, LEN(A2)))))) & " " & LEFT(A2, FIND(" ", A2) - 1), TRIM(MID(A2, FIND(",", A2) + 1, LEN(A2))) & " " & LEFT(A2, FIND(" ", A2) - 1)) -> NAHIARA ARCE | G2: 2 | H2: BENEGAS ACUÑA NAHIARA ABIGAIL
A3: ARCE CONTESSI, GUADALUPE MARIA LUJAN | B3: =IFERROR(TRIM(LEFT(MID(A3, FIND(",", A3) + 1, LEN(A3)), FIND(" ", TRIM(MID(A3, FIND(",", A3) + 1, LEN(A3)))))) & " " & LEFT(A3, FIND(" ", A3) - 1), TRIM(MID(A3, FIND(",", A3) + 1, LEN(A3))) & " " & LEFT(A3, FIND(" ", A3) - 1)) -> GUADALUPE ARCE | G3: 3 | H3: BENEGAS VELAZQUEZ EITHAN JESUS
A4: AYALA MAIDANA, ALMA ISABELLA | B4: =IFERROR(TRIM(LEFT(MID(A4, FIND(",", A4) + 1, LEN(A4)), FIND(" ", TRIM(MID(A4, FIND(",", A4) + 1, LEN(A4)))))) & " " & LEFT(A4, FIND(" ", A4) - 1), TRIM(MID(A4, FIND(",", A4) + 1, LEN(A4))) & " " & LEFT(A4, FIND(" ", A4) - 1)) -> ALMA AYALA | G4: 4 | H4: CABALLERO DIAZ LUCIA BELEN
A5: BARRETO AYALA, GUADALUPE MABEL | B5: =IFERROR(TRIM(LEFT(MID(A5, FIND(",", A5) + 1, LEN(A5)), FIND(" ", TRIM(MID(A5, FIND(",", A5) + 1, LEN(A5)))))) & " " & LEFT(A5, FIND(" ", A5) - 1), TRIM(MID(A5, FIND(",", A5) + 1, LEN(A5))) & " " & LEFT(A5, FIND(" ", A5) - 1)) -> GUADALUPE BARRETO | G5: 5 | H5: CAMPOS DOMINGUEZ AURORA JAZMIN
A6: BARRIOS MONGES, LUIS JESUS | B6: =IFERROR(TRIM(LEFT(MID(A6, FIND(",", A6) + 1, LEN(A6)), FIND(" ", TRIM(MID(A6, FIND(",", A6) + 1, LEN(A6)))))) & " " & LEFT(A6, FIND(" ", A6) - 1), TRIM(MID(A6, FIND(",", A6) + 1, LEN(A6))) & " " & LEFT(A6, FIND(" ", A6) - 1)) -> LUIS BARRIOS | G6: 6 | H6: COLARTE EVERS MAIRA JOHANA
A7: BENITEZ GIMENEZ, LUANA ISABEL | B7: =IFERROR(TRIM(LEFT(MID(A7, FIND(",", A7) + 1, LEN(A7)), FIND(" ", TRIM(MID(A7, FIND(",", A7) + 1, LEN(A7)))))) & " " & LEFT(A7, FIND(" ", A7) - 1), TRIM(MID(A7, FIND(",", A7) + 1, LEN(A7))) & " " & LEFT(A7, FIND(" ", A7) - 1)) -> LUANA BENITEZ | G7: 7 | H7: COLMAN RECALDE GIOVANNI JOAQUIN
A8: CABALLERO DIAZ, CARLOS RODRIGO | B8: =IFERROR(TRIM(LEFT(MID(A8, FIND(",", A8) + 1, LEN(A8)), FIND(" ", TRIM(MID(A8, FIND(",", A8) + 1, LEN(A8)))))) & " " & LEFT(A8, FIND(" ", A8) - 1), TRIM(MID(A8, FIND(",", A8) + 1, LEN(A8))) & " " & LEFT(A8, FIND(" ", A8) - 1)) -> CARLOS CABALLERO | G8: 8 | H8: DIAZ ACOSTA FRANCISCO BENJAMIN
A9: CACERES ROMAN, THAIS VICTORIA | B9: =IFERROR(TRIM(LEFT(MID(A9, FIND(",", A9) + 1, LEN(A9)), FIND(" ", TRIM(MID(A9, FIND(",", A9) + 1, LEN(A9)))))) & " " & LEFT(A9, FIND(" ", A9) - 1), TRIM(MID(A9, FIND(",", A9) + 1, LEN(A9))) & " " & LEFT(A9, FIND(" ", A9) - 1)) -> THAIS CACERES | G9: 9 | H9: ECHEVERRIA REIMER BLADIMIR
A10: DIAZ ACUÑA, MAXIMO ROMAN | B10: =IFERROR(TRIM(LEFT(MID(A10, FIND(",", A10) + 1, LEN(A10)), FIND(" ", TRIM(MID(A10, FIND(",", A10) + 1, LEN(A10)))))) & " " & LEFT(A10, FIND(" ", A10) - 1), TRIM(MID(A10, FIND(",", A10) + 1, LEN(A10))) & " " & LEFT(A10, FIND(" ", A10) - 1)) -> MAXIMO DIAZ | G10: 10 | H10: FERNANDEZ CABALLERO DAFNE AILEN
A11: ESTIGARRIBIA ESTIGARRIBIA, BASTTIAN JOSUE | B11: =IFERROR(TRIM(LEFT(MID(A11, FIND(",", A11) + 1, LEN(A11)), FIND(" ", TRIM(MID(A11, FIND(",", A11) + 1, LEN(A11)))))) & " " & LEFT(A11, FIND(" ", A11) - 1), TRIM(MID(A11, FIND(",", A11) + 1, LEN(A11))) & " " & LEFT(A11, FIND(" ", A11) - 1)) -> BASTTIAN ESTIGARRIBIA | G11: 11 | H11: FRANCO ARCE PABLO TADEO JESUS
A12: FERNANDEZ ARCE, IVONNE VIRGINIA | B12: =IFERROR(TRIM(LEFT(MID(A12, FIND(",", A12) + 1, LEN(A12)), FIND(" ", TRIM(MID(A12, FIND(",", A12) + 1, LEN(A12)))))) & " " & LEFT(A12, FIND(" ", A12) - 1), TRIM(MID(A12, FIND(",", A12) + 1, LEN(A12))) & " " & LEFT(A12, FIND(" ", A12) - 1)) -> IVONNE FERNANDEZ | G12: 12 | H12: GALEANO ARCE, AILANA MARIBEL
A13: FERNANDEZ TRINIDAD, EMILIA ARAMI | B13: =IFERROR(TRIM(LEFT(MID(A13, FIND(",", A13) + 1, LEN(A13)), FIND(" ", TRIM(MID(A13, FIND(",", A13) + 1, LEN(A13)))))) & " " & LEFT(A13, FIND(" ", A13) - 1), TRIM(MID(A13, FIND(",", A13) + 1, LEN(A13))) & " " & LEFT(A13, FIND(" ", A13) - 1)) -> EMILIA FERNANDEZ | G13: 13 | H13: GARCIA HELLIÓN, ANGELES KIARA
... A37: SALCEDO AYALA, CHRISTOPHER RODRIGO | B37: =IFERROR(TRIM(LEFT(MID(A37, FIND(",", A37) + 1, LEN(A37)), FIND(" ", TRIM(MID(A37, FIND(",", A37) + 1, LEN(A37)))))) & " " & LEFT(A37, FIND(" ", A37) - 1), TRIM(MID(A37, FIND(",", A37) + 1, LEN(A37))) & " " & LEFT(A37, FIND(" ", A37) - 1)) -> CHRISTOPHER SALCEDO | G37: 37 | H37: VILLALBA PINHO DYLAN ALEXANDER
A38: SAMANIEGO ROJAS, ALEX DAVID | B38: =IFERROR(TRIM(LEFT(MID(A38, FIND(",", A38) + 1, LEN(A38)), FIND(" ", TRIM(MID(A38, FIND(",", A38) + 1, LEN(A38)))))) & " " & LEFT(A38, FIND(" ", A38) - 1), TRIM(MID(A38, FIND(",", A38) + 1, LEN(A38))) & " " & LEFT(A38, FIND(" ", A38) - 1)) -> ALEX SAMANIEGO
A39: SANCHEZ SALINAS, ROBERT ELIAS | B39: =IFERROR(TRIM(LEFT(MID(A39, FIND(",", A39) + 1, LEN(A39)), FIND(" ", TRIM(MID(A39, FIND(",", A39) + 1, LEN(A39)))))) & " " & LEFT(A39, FIND(" ", A39) - 1), TRIM(MID(A39, FIND(",", A39) + 1, LEN(A39))) & " " & LEFT(A39, FIND(" ", A39) - 1)) -> ROBERT SANCHEZ
A40: SANTA CRUZ MONTONADO, MARIA FLORENCIA | B40: =IFERROR(TRIM(LEFT(MID(A40, FIND(",", A40) + 1, LEN(A40)), FIND(" ", TRIM(MID(A40, FIND(",", A40) + 1, LEN(A40)))))) & " " & LEFT(A40, FIND(" ", A40) - 1), TRIM(MID(A40, FIND(",", A40) + 1, LEN(A40))) & " " & LEFT(A40, FIND(" ", A40) - 1)) -> MARIA SANTA
A41: SILVA GARCETE, FREDY MISAEL | B41: =IFERROR(TRIM(LEFT(MID(A41, FIND(",", A41) + 1, LEN(A41)), FIND(" ", TRIM(MID(A41, FIND(",", A41) + 1, LEN(A41)))))) & " " & LEFT(A41, FIND(" ", A41) - 1), TRIM(MID(A41, FIND(",", A41) + 1, LEN(A41))) & " " & LEFT(A41, FIND(" ", A41) - 1)) -> FREDY SILVA
A42: VERA ALCARAZ, LIZZIE CAROLINA | B42: =IFERROR(TRIM(LEFT(MID(A42, FIND(",", A42) + 1, LEN(A42)), FIND(" ", TRIM(MID(A42, FIND(",", A42) + 1, LEN(A42)))))) & " " & LEFT(A42, FIND(" ", A42) - 1), TRIM(MID(A42, FIND(",", A42) + 1, LEN(A42))) & " " & LEFT(A42, FIND(" ", A42) - 1)) -> LIZZIE VERA
A43: VILLASANTI GONZALEZ, JONATHAN JOSIAS | B43: =IFERROR(TRIM(LEFT(MID(A43, FIND(",", A43) + 1, LEN(A43)), FIND(" ", TRIM(MID(A43, FIND(",", A43) + 1, LEN(A43)))))) & " " & LEFT(A43, FIND(" ", A43) - 1), TRIM(MID(A43, FIND(",", A43) + 1, LEN(A43))) & " " & LEFT(A43, FIND(" ", A43) - 1)) -> JONATHAN VILLASANTI
A44: DUARTE CARDOZO, THIAGO BENJAMIIN | B44: =IFERROR(TRIM(LEFT(MID(A44, FIND(",", A44) + 1, LEN(A44)), FIND(" ", TRIM(MID(A44, FIND(",", A44) + 1, LEN(A44)))))) & " " & LEFT(A44, FIND(" ", A44) - 1), TRIM(MID(A44, FIND(",", A44) + 1, LEN(A44))) & " " & LEFT(A44, FIND(" ", A44) - 1)) -> THIAGO DUARTE
